{
    "layers": {
        "OCO_2_Orbit_Dsc": {
            "id":       "OCO_2_Orbit_Dsc",
            "title":    "Orbital Track (Descending/Night)",
            "subtitle": "Space-Track.org / OCO-2",
            "group":    "overlays",
            "format":   "image/png",
            "type":     "wms",
            "tileSize": [512, 512],
            "period":   "daily",

            "startDate": "2014-07-02",

            "projections": {
                "antarctic": {
                    "source":   "GIBS:wms"
                },
                "arctic": {
                    "source":   "GIBS:wms"
                },
                "geographic": {
                    "source":   "GIBS:wms"
                }
            },

            "palette": {
                "id":     "OCO_2_Orbit_Asc",
                "immutable": true
            }
        }
    }
}
