<?xml version="1.0" encoding="UTF-8"?>
<ColorMap xmlns:xsi="http://www.w3.org/2001/XMLSchema-instance"
          xsi:noNamespaceSchemaLocation="http://map1.vis.earthdata.nasa.gov/schema/ColorMap_v1.0.xsd"
          units="°C">
  <ColorMapEntry rgb="0,0,0" transparent="true" label="No Data" />
  <ColorMapEntry rgb="43,0,26" transparent="false" value="[2.00,2.15)" label="2.00 – 2.15 °C" />
  <ColorMapEntry rgb="46,0,29" transparent="false" value="[2.15,2.30)" label="2.15 – 2.30 °C" />
  <ColorMapEntry rgb="49,0,32" transparent="false" value="[2.30,2.45)" label="2.30 – 2.45 °C" />
  <ColorMapEntry rgb="52,0,35" transparent="false" value="[2.45,2.60)" label="2.45 – 2.60 °C" />
  <ColorMapEntry rgb="56,1,39" transparent="false" value="[2.60,2.75)" label="2.60 – 2.75 °C" />
  <ColorMapEntry rgb="59,1,42" transparent="false" value="[2.75,2.90)" label="2.75 – 2.90 °C" />
  <ColorMapEntry rgb="62,1,45" transparent="false" value="[2.90,3.05)" label="2.90 – 3.05 °C" />
  <ColorMapEntry rgb="65,1,48" transparent="false" value="[3.05,3.20)" label="3.05 – 3.20 °C" />
  <ColorMapEntry rgb="68,2,52" transparent="false" value="[3.20,3.35)" label="3.20 – 3.35 °C" />
  <ColorMapEntry rgb="71,2,56" transparent="false" value="[3.35,3.50)" label="3.35 – 3.50 °C" />
  <ColorMapEntry rgb="75,2,61" transparent="false" value="[3.50,3.65)" label="3.50 – 3.65 °C" />
  <ColorMapEntry rgb="78,2,65" transparent="false" value="[3.65,3.80)" label="3.65 – 3.80 °C" />
  <ColorMapEntry rgb="82,3,70" transparent="false" value="[3.80,3.95)" label="3.80 – 3.95 °C" />
  <ColorMapEntry rgb="85,3,74" transparent="false" value="[3.95,4.10)" label="3.95 – 4.10 °C" />
  <ColorMapEntry rgb="89,3,78" transparent="false" value="[4.10,4.25)" label="4.10 – 4.25 °C" />
  <ColorMapEntry rgb="93,3,82" transparent="false" value="[4.25,4.40)" label="4.25 – 4.40 °C" />
  <ColorMapEntry rgb="97,4,87" transparent="false" value="[4.40,4.55)" label="4.40 – 4.55 °C" />
  <ColorMapEntry rgb="100,4,91" transparent="false" value="[4.55,4.70)" label="4.55 – 4.70 °C" />
  <ColorMapEntry rgb="104,5,96" transparent="false" value="[4.70,4.85)" label="4.70 – 4.85 °C" />
  <ColorMapEntry rgb="107,5,100" transparent="false" value="[4.85,5.00)" label="4.85 – 5.00 °C" />
  <ColorMapEntry rgb="111,6,105" transparent="false" value="[5.00,5.15)" label="5.00 – 5.15 °C" />
  <ColorMapEntry rgb="114,6,109" transparent="false" value="[5.15,5.30)" label="5.15 – 5.30 °C" />
  <ColorMapEntry rgb="118,6,113" transparent="false" value="[5.30,5.45)" label="5.30 – 5.45 °C" />
  <ColorMapEntry rgb="122,6,117" transparent="false" value="[5.45,5.60)" label="5.45 – 5.60 °C" />
  <ColorMapEntry rgb="126,7,122" transparent="false" value="[5.60,5.75)" label="5.60 – 5.75 °C" />
  <ColorMapEntry rgb="124,7,121" transparent="false" value="[5.75,5.90)" label="5.75 – 5.90 °C" />
  <ColorMapEntry rgb="123,7,121" transparent="false" value="[5.90,6.05)" label="5.90 – 6.05 °C" />
  <ColorMapEntry rgb="121,7,120" transparent="false" value="[6.05,6.20)" label="6.05 – 6.20 °C" />
  <ColorMapEntry rgb="120,8,120" transparent="false" value="[6.20,6.35)" label="6.20 – 6.35 °C" />
  <ColorMapEntry rgb="115,8,117" transparent="false" value="[6.35,6.50)" label="6.35 – 6.50 °C" />
  <ColorMapEntry rgb="111,8,115" transparent="false" value="[6.50,6.65)" label="6.50 – 6.65 °C" />
  <ColorMapEntry rgb="106,8,112" transparent="false" value="[6.65,6.80)" label="6.65 – 6.80 °C" />
  <ColorMapEntry rgb="102,9,110" transparent="false" value="[6.80,6.95)" label="6.80 – 6.95 °C" />
  <ColorMapEntry rgb="97,9,107" transparent="false" value="[6.95,7.10)" label="6.95 – 7.10 °C" />
  <ColorMapEntry rgb="93,9,105" transparent="false" value="[7.10,7.25)" label="7.10 – 7.25 °C" />
  <ColorMapEntry rgb="88,9,103" transparent="false" value="[7.25,7.40)" label="7.25 – 7.40 °C" />
  <ColorMapEntry rgb="84,10,101" transparent="false" value="[7.40,7.55)" label="7.40 – 7.55 °C" />
  <ColorMapEntry rgb="79,10,98" transparent="false" value="[7.55,7.70)" label="7.55 – 7.70 °C" />
  <ColorMapEntry rgb="75,10,96" transparent="false" value="[7.70,7.85)" label="7.70 – 7.85 °C" />
  <ColorMapEntry rgb="70,10,93" transparent="false" value="[7.85,8.00)" label="7.85 – 8.00 °C" />
  <ColorMapEntry rgb="66,11,91" transparent="false" value="[8.00,8.15)" label="8.00 – 8.15 °C" />
  <ColorMapEntry rgb="61,11,88" transparent="false" value="[8.15,8.30)" label="8.15 – 8.30 °C" />
  <ColorMapEntry rgb="57,11,86" transparent="false" value="[8.30,8.45)" label="8.30 – 8.45 °C" />
  <ColorMapEntry rgb="52,11,84" transparent="false" value="[8.45,8.60)" label="8.45 – 8.60 °C" />
  <ColorMapEntry rgb="48,12,82" transparent="false" value="[8.60,8.75)" label="8.60 – 8.75 °C" />
  <ColorMapEntry rgb="43,12,79" transparent="false" value="[8.75,8.90)" label="8.75 – 8.90 °C" />
  <ColorMapEntry rgb="39,12,77" transparent="false" value="[8.90,9.05)" label="8.90 – 9.05 °C" />
  <ColorMapEntry rgb="34,12,74" transparent="false" value="[9.05,9.20)" label="9.05 – 9.20 °C" />
  <ColorMapEntry rgb="30,13,72" transparent="false" value="[9.20,9.35)" label="9.20 – 9.35 °C" />
  <ColorMapEntry rgb="30,15,75" transparent="false" value="[9.35,9.50)" label="9.35 – 9.50 °C" />
  <ColorMapEntry rgb="30,18,78" transparent="false" value="[9.50,9.65)" label="9.50 – 9.65 °C" />
  <ColorMapEntry rgb="30,20,81" transparent="false" value="[9.65,9.80)" label="9.65 – 9.80 °C" />
  <ColorMapEntry rgb="31,23,85" transparent="false" value="[9.80,9.95)" label="9.80 – 9.95 °C" />
  <ColorMapEntry rgb="31,25,88" transparent="false" value="[9.95,10.10)" label="9.95 – 10.10 °C" />
  <ColorMapEntry rgb="31,27,91" transparent="false" value="[10.10,10.25)" label="10.10 – 10.25 °C" />
  <ColorMapEntry rgb="31,29,94" transparent="false" value="[10.25,10.40)" label="10.25 – 10.40 °C" />
  <ColorMapEntry rgb="31,32,98" transparent="false" value="[10.40,10.55)" label="10.40 – 10.55 °C" />
  <ColorMapEntry rgb="31,34,101" transparent="false" value="[10.55,10.70)" label="10.55 – 10.70 °C" />
  <ColorMapEntry rgb="31,37,104" transparent="false" value="[10.70,10.85)" label="10.70 – 10.85 °C" />
  <ColorMapEntry rgb="31,39,107" transparent="false" value="[10.85,11.00)" label="10.85 – 11.00 °C" />
  <ColorMapEntry rgb="32,42,111" transparent="false" value="[11.00,11.15)" label="11.00 – 11.15 °C" />
  <ColorMapEntry rgb="32,44,114" transparent="false" value="[11.15,11.30)" label="11.15 – 11.30 °C" />
  <ColorMapEntry rgb="32,46,118" transparent="false" value="[11.30,11.45)" label="11.30 – 11.45 °C" />
  <ColorMapEntry rgb="32,48,121" transparent="false" value="[11.45,11.60)" label="11.45 – 11.60 °C" />
  <ColorMapEntry rgb="32,51,125" transparent="false" value="[11.60,11.75)" label="11.60 – 11.75 °C" />
  <ColorMapEntry rgb="32,53,128" transparent="false" value="[11.75,11.90)" label="11.75 – 11.90 °C" />
  <ColorMapEntry rgb="32,56,131" transparent="false" value="[11.90,12.05)" label="11.90 – 12.05 °C" />
  <ColorMapEntry rgb="32,58,134" transparent="false" value="[12.05,12.20)" label="12.05 – 12.20 °C" />
  <ColorMapEntry rgb="33,61,138" transparent="false" value="[12.20,12.35)" label="12.20 – 12.35 °C" />
  <ColorMapEntry rgb="33,63,141" transparent="false" value="[12.35,12.50)" label="12.35 – 12.50 °C" />
  <ColorMapEntry rgb="33,65,144" transparent="false" value="[12.50,12.65)" label="12.50 – 12.65 °C" />
  <ColorMapEntry rgb="33,67,147" transparent="false" value="[12.65,12.80)" label="12.65 – 12.80 °C" />
  <ColorMapEntry rgb="33,70,151" transparent="false" value="[12.80,12.95)" label="12.80 – 12.95 °C" />
  <ColorMapEntry rgb="33,72,154" transparent="false" value="[12.95,13.10)" label="12.95 – 13.10 °C" />
  <ColorMapEntry rgb="33,75,157" transparent="false" value="[13.10,13.25)" label="13.10 – 13.25 °C" />
  <ColorMapEntry rgb="33,77,160" transparent="false" value="[13.25,13.40)" label="13.25 – 13.40 °C" />
  <ColorMapEntry rgb="34,80,164" transparent="false" value="[13.40,13.55)" label="13.40 – 13.55 °C" />
  <ColorMapEntry rgb="34,83,167" transparent="false" value="[13.55,13.70)" label="13.55 – 13.70 °C" />
  <ColorMapEntry rgb="35,87,170" transparent="false" value="[13.70,13.85)" label="13.70 – 13.85 °C" />
  <ColorMapEntry rgb="35,90,173" transparent="false" value="[13.85,14.00)" label="13.85 – 14.00 °C" />
  <ColorMapEntry rgb="36,94,177" transparent="false" value="[14.00,14.15)" label="14.00 – 14.15 °C" />
  <ColorMapEntry rgb="36,97,180" transparent="false" value="[14.15,14.30)" label="14.15 – 14.30 °C" />
  <ColorMapEntry rgb="37,101,183" transparent="false" value="[14.30,14.45)" label="14.30 – 14.45 °C" />
  <ColorMapEntry rgb="38,105,186" transparent="false" value="[14.45,14.60)" label="14.45 – 14.60 °C" />
  <ColorMapEntry rgb="39,109,190" transparent="false" value="[14.60,14.75)" label="14.60 – 14.75 °C" />
  <ColorMapEntry rgb="39,112,193" transparent="false" value="[14.75,14.90)" label="14.75 – 14.90 °C" />
  <ColorMapEntry rgb="40,116,196" transparent="false" value="[14.90,15.05)" label="14.90 – 15.05 °C" />
  <ColorMapEntry rgb="40,119,199" transparent="false" value="[15.05,15.20)" label="15.05 – 15.20 °C" />
  <ColorMapEntry rgb="41,123,203" transparent="false" value="[15.20,15.35)" label="15.20 – 15.35 °C" />
  <ColorMapEntry rgb="41,126,206" transparent="false" value="[15.35,15.50)" label="15.35 – 15.50 °C" />
  <ColorMapEntry rgb="42,130,209" transparent="false" value="[15.50,15.65)" label="15.50 – 15.65 °C" />
  <ColorMapEntry rgb="42,133,212" transparent="false" value="[15.65,15.80)" label="15.65 – 15.80 °C" />
  <ColorMapEntry rgb="43,137,216" transparent="false" value="[15.80,15.95)" label="15.80 – 15.95 °C" />
  <ColorMapEntry rgb="43,140,219" transparent="false" value="[15.95,16.10)" label="15.95 – 16.10 °C" />
  <ColorMapEntry rgb="44,144,222" transparent="false" value="[16.10,16.25)" label="16.10 – 16.25 °C" />
  <ColorMapEntry rgb="44,147,225" transparent="false" value="[16.25,16.40)" label="16.25 – 16.40 °C" />
  <ColorMapEntry rgb="45,151,229" transparent="false" value="[16.40,16.55)" label="16.40 – 16.55 °C" />
  <ColorMapEntry rgb="45,154,232" transparent="false" value="[16.55,16.70)" label="16.55 – 16.70 °C" />
  <ColorMapEntry rgb="46,158,235" transparent="false" value="[16.70,16.85)" label="16.70 – 16.85 °C" />
  <ColorMapEntry rgb="47,162,238" transparent="false" value="[16.85,17.00)" label="16.85 – 17.00 °C" />
  <ColorMapEntry rgb="48,166,242" transparent="false" value="[17.00,17.15)" label="17.00 – 17.15 °C" />
  <ColorMapEntry rgb="48,169,245" transparent="false" value="[17.15,17.30)" label="17.15 – 17.30 °C" />
  <ColorMapEntry rgb="49,173,248" transparent="false" value="[17.30,17.45)" label="17.30 – 17.45 °C" />
  <ColorMapEntry rgb="49,176,251" transparent="false" value="[17.45,17.60)" label="17.45 – 17.60 °C" />
  <ColorMapEntry rgb="50,180,255" transparent="false" value="[17.60,17.75)" label="17.60 – 17.75 °C" />
  <ColorMapEntry rgb="47,177,233" transparent="false" value="[17.75,17.90)" label="17.75 – 17.90 °C" />
  <ColorMapEntry rgb="45,174,212" transparent="false" value="[17.90,18.05)" label="17.90 – 18.05 °C" />
  <ColorMapEntry rgb="42,171,191" transparent="false" value="[18.05,18.20)" label="18.05 – 18.20 °C" />
  <ColorMapEntry rgb="40,169,170" transparent="false" value="[18.20,18.35)" label="18.20 – 18.35 °C" />
  <ColorMapEntry rgb="37,166,148" transparent="false" value="[18.35,18.50)" label="18.35 – 18.50 °C" />
  <ColorMapEntry rgb="35,164,127" transparent="false" value="[18.50,18.65)" label="18.50 – 18.65 °C" />
  <ColorMapEntry rgb="32,161,106" transparent="false" value="[18.65,18.80)" label="18.65 – 18.80 °C" />
  <ColorMapEntry rgb="30,159,85" transparent="false" value="[18.80,18.95)" label="18.80 – 18.95 °C" />
  <ColorMapEntry rgb="27,164,63" transparent="false" value="[18.95,19.10)" label="18.95 – 19.10 °C" />
  <ColorMapEntry rgb="25,169,42" transparent="false" value="[19.10,19.25)" label="19.10 – 19.25 °C" />
  <ColorMapEntry rgb="22,174,21" transparent="false" value="[19.25,19.40)" label="19.25 – 19.40 °C" />
  <ColorMapEntry rgb="20,180,0" transparent="false" value="[19.40,19.55)" label="19.40 – 19.55 °C" />
  <ColorMapEntry rgb="31,183,0" transparent="false" value="[19.55,19.70)" label="19.55 – 19.70 °C" />
  <ColorMapEntry rgb="43,187,0" transparent="false" value="[19.70,19.85)" label="19.70 – 19.85 °C" />
  <ColorMapEntry rgb="55,191,0" transparent="false" value="[19.85,20.00)" label="19.85 – 20.00 °C" />
  <ColorMapEntry rgb="67,195,0" transparent="false" value="[20.00,20.15)" label="20.00 – 20.15 °C" />
  <ColorMapEntry rgb="78,198,0" transparent="false" value="[20.15,20.30)" label="20.15 – 20.30 °C" />
  <ColorMapEntry rgb="90,202,0" transparent="false" value="[20.30,20.45)" label="20.30 – 20.45 °C" />
  <ColorMapEntry rgb="102,206,0" transparent="false" value="[20.45,20.60)" label="20.45 – 20.60 °C" />
  <ColorMapEntry rgb="114,210,0" transparent="false" value="[20.60,20.75)" label="20.60 – 20.75 °C" />
  <ColorMapEntry rgb="125,213,0" transparent="false" value="[20.75,20.90)" label="20.75 – 20.90 °C" />
  <ColorMapEntry rgb="137,217,0" transparent="false" value="[20.90,21.05)" label="20.90 – 21.05 °C" />
  <ColorMapEntry rgb="149,221,0" transparent="false" value="[21.05,21.20)" label="21.05 – 21.20 °C" />
  <ColorMapEntry rgb="161,225,0" transparent="false" value="[21.20,21.35)" label="21.20 – 21.35 °C" />
  <ColorMapEntry rgb="172,228,0" transparent="false" value="[21.35,21.50)" label="21.35 – 21.50 °C" />
  <ColorMapEntry rgb="184,232,0" transparent="false" value="[21.50,21.65)" label="21.50 – 21.65 °C" />
  <ColorMapEntry rgb="196,236,0" transparent="false" value="[21.65,21.80)" label="21.65 – 21.80 °C" />
  <ColorMapEntry rgb="208,240,0" transparent="false" value="[21.80,21.95)" label="21.80 – 21.95 °C" />
  <ColorMapEntry rgb="219,243,0" transparent="false" value="[21.95,22.10)" label="21.95 – 22.10 °C" />
  <ColorMapEntry rgb="231,247,0" transparent="false" value="[22.10,22.25)" label="22.10 – 22.25 °C" />
  <ColorMapEntry rgb="243,251,0" transparent="false" value="[22.25,22.40)" label="22.25 – 22.40 °C" />
  <ColorMapEntry rgb="255,255,0" transparent="false" value="[22.40,22.55)" label="22.40 – 22.55 °C" />
  <ColorMapEntry rgb="255,249,0" transparent="false" value="[22.55,22.70)" label="22.55 – 22.70 °C" />
  <ColorMapEntry rgb="255,243,0" transparent="false" value="[22.70,22.85)" label="22.70 – 22.85 °C" />
  <ColorMapEntry rgb="255,237,0" transparent="false" value="[22.85,23.00)" label="22.85 – 23.00 °C" />
  <ColorMapEntry rgb="255,232,0" transparent="false" value="[23.00,23.15)" label="23.00 – 23.15 °C" />
  <ColorMapEntry rgb="255,226,0" transparent="false" value="[23.15,23.30)" label="23.15 – 23.30 °C" />
  <ColorMapEntry rgb="255,220,0" transparent="false" value="[23.30,23.45)" label="23.30 – 23.45 °C" />
  <ColorMapEntry rgb="255,214,0" transparent="false" value="[23.45,23.60)" label="23.45 – 23.60 °C" />
  <ColorMapEntry rgb="255,209,0" transparent="false" value="[23.60,23.75)" label="23.60 – 23.75 °C" />
  <ColorMapEntry rgb="255,203,0" transparent="false" value="[23.75,23.90)" label="23.75 – 23.90 °C" />
  <ColorMapEntry rgb="255,197,0" transparent="false" value="[23.90,24.05)" label="23.90 – 24.05 °C" />
  <ColorMapEntry rgb="255,191,0" transparent="false" value="[24.05,24.20)" label="24.05 – 24.20 °C" />
  <ColorMapEntry rgb="255,186,0" transparent="false" value="[24.20,24.35)" label="24.20 – 24.35 °C" />
  <ColorMapEntry rgb="255,180,0" transparent="false" value="[24.35,24.50)" label="24.35 – 24.50 °C" />
  <ColorMapEntry rgb="255,174,0" transparent="false" value="[24.50,24.65)" label="24.50 – 24.65 °C" />
  <ColorMapEntry rgb="255,168,0" transparent="false" value="[24.65,24.80)" label="24.65 – 24.80 °C" />
  <ColorMapEntry rgb="255,163,0" transparent="false" value="[24.80,24.95)" label="24.80 – 24.95 °C" />
  <ColorMapEntry rgb="255,157,0" transparent="false" value="[24.95,25.10)" label="24.95 – 25.10 °C" />
  <ColorMapEntry rgb="255,151,0" transparent="false" value="[25.10,25.25)" label="25.10 – 25.25 °C" />
  <ColorMapEntry rgb="255,145,0" transparent="false" value="[25.25,25.40)" label="25.25 – 25.40 °C" />
  <ColorMapEntry rgb="255,140,0" transparent="false" value="[25.40,25.55)" label="25.40 – 25.55 °C" />
  <ColorMapEntry rgb="255,134,0" transparent="false" value="[25.55,25.70)" label="25.55 – 25.70 °C" />
  <ColorMapEntry rgb="255,128,0" transparent="false" value="[25.70,25.85)" label="25.70 – 25.85 °C" />
  <ColorMapEntry rgb="255,122,0" transparent="false" value="[25.85,26.00)" label="25.85 – 26.00 °C" />
  <ColorMapEntry rgb="255,117,0" transparent="false" value="[26.00,26.15)" label="26.00 – 26.15 °C" />
  <ColorMapEntry rgb="252,113,0" transparent="false" value="[26.15,26.30)" label="26.15 – 26.30 °C" />
  <ColorMapEntry rgb="250,109,0" transparent="false" value="[26.30,26.45)" label="26.30 – 26.45 °C" />
  <ColorMapEntry rgb="248,105,0" transparent="false" value="[26.45,26.60)" label="26.45 – 26.60 °C" />
  <ColorMapEntry rgb="246,102,0" transparent="false" value="[26.60,26.75)" label="26.60 – 26.75 °C" />
  <ColorMapEntry rgb="244,98,0" transparent="false" value="[26.75,26.90)" label="26.75 – 26.90 °C" />
  <ColorMapEntry rgb="242,94,0" transparent="false" value="[26.90,27.05)" label="26.90 – 27.05 °C" />
  <ColorMapEntry rgb="240,90,0" transparent="false" value="[27.05,27.20)" label="27.05 – 27.20 °C" />
  <ColorMapEntry rgb="238,86,0" transparent="false" value="[27.20,27.35)" label="27.20 – 27.35 °C" />
  <ColorMapEntry rgb="235,82,0" transparent="false" value="[27.35,27.50)" label="27.35 – 27.50 °C" />
  <ColorMapEntry rgb="233,78,0" transparent="false" value="[27.50,27.65)" label="27.50 – 27.65 °C" />
  <ColorMapEntry rgb="231,74,0" transparent="false" value="[27.65,27.80)" label="27.65 – 27.80 °C" />
  <ColorMapEntry rgb="229,71,0" transparent="false" value="[27.80,27.95)" label="27.80 – 27.95 °C" />
  <ColorMapEntry rgb="227,67,0" transparent="false" value="[27.95,28.10)" label="27.95 – 28.10 °C" />
  <ColorMapEntry rgb="225,63,0" transparent="false" value="[28.10,28.25)" label="28.10 – 28.25 °C" />
  <ColorMapEntry rgb="223,59,0" transparent="false" value="[28.25,28.40)" label="28.25 – 28.40 °C" />
  <ColorMapEntry rgb="221,55,0" transparent="false" value="[28.40,28.55)" label="28.40 – 28.55 °C" />
  <ColorMapEntry rgb="218,51,0" transparent="false" value="[28.55,28.70)" label="28.55 – 28.70 °C" />
  <ColorMapEntry rgb="216,47,0" transparent="false" value="[28.70,28.85)" label="28.70 – 28.85 °C" />
  <ColorMapEntry rgb="214,43,0" transparent="false" value="[28.85,29.00)" label="28.85 – 29.00 °C" />
  <ColorMapEntry rgb="212,40,0" transparent="false" value="[29.00,29.15)" label="29.00 – 29.15 °C" />
  <ColorMapEntry rgb="206,38,0" transparent="false" value="[29.15,29.30)" label="29.15 – 29.30 °C" />
  <ColorMapEntry rgb="200,36,0" transparent="false" value="[29.30,29.45)" label="29.30 – 29.45 °C" />
  <ColorMapEntry rgb="194,34,0" transparent="false" value="[29.45,29.60)" label="29.45 – 29.60 °C" />
  <ColorMapEntry rgb="189,32,0" transparent="false" value="[29.60,29.75)" label="29.60 – 29.75 °C" />
  <ColorMapEntry rgb="183,30,0" transparent="false" value="[29.75,29.90)" label="29.75 – 29.90 °C" />
  <ColorMapEntry rgb="178,28,0" transparent="false" value="[29.90,30.05)" label="29.90 – 30.05 °C" />
  <ColorMapEntry rgb="172,26,0" transparent="false" value="[30.05,30.20)" label="30.05 – 30.20 °C" />
  <ColorMapEntry rgb="167,24,0" transparent="false" value="[30.20,30.35)" label="30.20 – 30.35 °C" />
  <ColorMapEntry rgb="161,22,0" transparent="false" value="[30.35,30.50)" label="30.35 – 30.50 °C" />
  <ColorMapEntry rgb="155,20,0" transparent="false" value="[30.50,30.65)" label="30.50 – 30.65 °C" />
  <ColorMapEntry rgb="149,18,0" transparent="false" value="[30.65,30.80)" label="30.65 – 30.80 °C" />
  <ColorMapEntry rgb="144,16,0" transparent="false" value="[30.80,30.95)" label="30.80 – 30.95 °C" />
  <ColorMapEntry rgb="138,14,0" transparent="false" value="[30.95,31.10)" label="30.95 – 31.10 °C" />
  <ColorMapEntry rgb="133,12,0" transparent="false" value="[31.10,31.25)" label="31.10 – 31.25 °C" />
  <ColorMapEntry rgb="127,10,0" transparent="false" value="[31.25,31.40)" label="31.25 – 31.40 °C" />
  <ColorMapEntry rgb="122,8,0" transparent="false" value="[31.40,31.55)" label="31.40 – 31.55 °C" />
  <ColorMapEntry rgb="122,8,0" transparent="false" value="[31.55,31.70)" label="31.55 – 31.70 °C" />
  <ColorMapEntry rgb="122,8,0" transparent="false" value="[31.70,31.85)" label="31.70 – 31.85 °C" />
  <ColorMapEntry rgb="122,8,0" transparent="false" value="[31.85,32.00)" label="31.85 – 32.00 °C" />
</ColorMap>
