<?xml version="1.0" encoding="UTF-8"?>
<ColorMap xmlns:xsi="http://www.w3.org/2001/XMLSchema-instance"
          xsi:noNamespaceSchemaLocation="http://map1.vis.earthdata.nasa.gov/schema/ColorMap_v1.0.xsd"
          units="">
  <ColorMapEntry rgb="220,220,255" transparent="true" label="Fill" />
  <ColorMapEntry rgb="184,0,185" transparent="false" value="[0.01,1)" label="0.01 – 1.00" />
  <ColorMapEntry rgb="182,0,184" transparent="false" value="[1,1.038)" label="1.00 – 1.04" />
  <ColorMapEntry rgb="180,0,183" transparent="false" value="[1.038,1.077)" label="1.04 – 1.08" />
  <ColorMapEntry rgb="178,0,182" transparent="false" value="[1.077,1.118)" label="1.08 – 1.12" />
  <ColorMapEntry rgb="176,0,181" transparent="false" value="[1.118,1.16)" label="1.12 – 1.16" />
  <ColorMapEntry rgb="174,0,180" transparent="false" value="[1.16,1.204)" label="1.16 – 1.20" />
  <ColorMapEntry rgb="172,0,179" transparent="false" value="[1.204,1.25)" label="1.20 – 1.25" />
  <ColorMapEntry rgb="170,0,178" transparent="false" value="[1.25,1.297)" label="1.25 – 1.30" />
  <ColorMapEntry rgb="168,0,177" transparent="false" value="[1.297,1.346)" label="1.30 – 1.35" />
  <ColorMapEntry rgb="166,0,176" transparent="false" value="[1.346,1.397)" label="1.35 – 1.40" />
  <ColorMapEntry rgb="164,0,175" transparent="false" value="[1.397,1.45)" label="1.40 – 1.45" />
  <ColorMapEntry rgb="162,0,174" transparent="false" value="[1.45,1.505)" label="1.45 – 1.50" />
  <ColorMapEntry rgb="160,0,173" transparent="false" value="[1.505,1.562)" label="1.50 – 1.56" />
  <ColorMapEntry rgb="158,0,172" transparent="false" value="[1.562,1.621)" label="1.56 – 1.62" />
  <ColorMapEntry rgb="156,0,171" transparent="false" value="[1.621,1.682)" label="1.62 – 1.68" />
  <ColorMapEntry rgb="154,0,170" transparent="false" value="[1.682,1.746)" label="1.68 – 1.75" />
  <ColorMapEntry rgb="152,0,169" transparent="false" value="[1.746,1.812)" label="1.75 – 1.81" />
  <ColorMapEntry rgb="150,0,168" transparent="false" value="[1.812,1.88)" label="1.81 – 1.88" />
  <ColorMapEntry rgb="148,0,167" transparent="false" value="[1.88,1.951)" label="1.88 – 1.95" />
  <ColorMapEntry rgb="146,0,166" transparent="false" value="[1.951,2.025)" label="1.95 – 2.02" />
  <ColorMapEntry rgb="144,0,165" transparent="false" value="[2.025,2.102)" label="2.02 – 2.10" />
  <ColorMapEntry rgb="142,0,165" transparent="false" value="[2.102,2.181)" label="2.10 – 2.18" />
  <ColorMapEntry rgb="140,0,164" transparent="false" value="[2.181,2.264)" label="2.18 – 2.26" />
  <ColorMapEntry rgb="138,0,163" transparent="false" value="[2.264,2.349)" label="2.26 – 2.35" />
  <ColorMapEntry rgb="136,0,162" transparent="false" value="[2.349,2.438)" label="2.35 – 2.44" />
  <ColorMapEntry rgb="134,0,161" transparent="false" value="[2.438,2.531)" label="2.44 – 2.53" />
  <ColorMapEntry rgb="132,0,160" transparent="false" value="[2.531,2.626)" label="2.53 – 2.63" />
  <ColorMapEntry rgb="130,0,159" transparent="false" value="[2.626,2.726)" label="2.63 – 2.73" />
  <ColorMapEntry rgb="128,0,158" transparent="false" value="[2.726,2.829)" label="2.73 – 2.83" />
  <ColorMapEntry rgb="126,0,157" transparent="false" value="[2.829,2.936)" label="2.83 – 2.94" />
  <ColorMapEntry rgb="124,0,156" transparent="false" value="[2.936,3.047)" label="2.94 – 3.05" />
  <ColorMapEntry rgb="122,0,155" transparent="false" value="[3.047,3.162)" label="3.05 – 3.16" />
  <ColorMapEntry rgb="120,0,154" transparent="false" value="[3.162,3.282)" label="3.16 – 3.28" />
  <ColorMapEntry rgb="118,0,153" transparent="false" value="[3.282,3.406)" label="3.28 – 3.41" />
  <ColorMapEntry rgb="116,0,152" transparent="false" value="[3.406,3.535)" label="3.41 – 3.54" />
  <ColorMapEntry rgb="114,0,151" transparent="false" value="[3.535,3.669)" label="3.54 – 3.67" />
  <ColorMapEntry rgb="112,0,150" transparent="false" value="[3.669,3.808)" label="3.67 – 3.81" />
  <ColorMapEntry rgb="110,0,149" transparent="false" value="[3.808,3.952)" label="3.81 – 3.95" />
  <ColorMapEntry rgb="108,0,148" transparent="false" value="[3.952,4.101)" label="3.95 – 4.10" />
  <ColorMapEntry rgb="106,0,147" transparent="false" value="[4.101,4.256)" label="4.10 – 4.26" />
  <ColorMapEntry rgb="104,0,146" transparent="false" value="[4.256,4.417)" label="4.26 – 4.42" />
  <ColorMapEntry rgb="102,0,145" transparent="false" value="[4.417,4.584)" label="4.42 – 4.58" />
  <ColorMapEntry rgb="100,0,145" transparent="false" value="[4.584,4.758)" label="4.58 – 4.76" />
  <ColorMapEntry rgb="97,0,147" transparent="false" value="[4.758,4.938)" label="4.76 – 4.94" />
  <ColorMapEntry rgb="95,0,150" transparent="false" value="[4.938,5.125)" label="4.94 – 5.12" />
  <ColorMapEntry rgb="92,0,152" transparent="false" value="[5.125,5.319)" label="5.12 – 5.32" />
  <ColorMapEntry rgb="90,3,155" transparent="false" value="[5.319,5.52)" label="5.32 – 5.52" />
  <ColorMapEntry rgb="88,6,158" transparent="false" value="[5.52,5.729)" label="5.52 – 5.73" />
  <ColorMapEntry rgb="85,9,160" transparent="false" value="[5.729,5.946)" label="5.73 – 5.95" />
  <ColorMapEntry rgb="83,12,163" transparent="false" value="[5.946,6.171)" label="5.95 – 6.17" />
  <ColorMapEntry rgb="80,15,165" transparent="false" value="[6.171,6.404)" label="6.17 – 6.40" />
  <ColorMapEntry rgb="78,18,168" transparent="false" value="[6.404,6.646)" label="6.40 – 6.65" />
  <ColorMapEntry rgb="76,22,171" transparent="false" value="[6.646,6.898)" label="6.65 – 6.90" />
  <ColorMapEntry rgb="73,25,173" transparent="false" value="[6.898,7.159)" label="6.90 – 7.16" />
  <ColorMapEntry rgb="71,28,176" transparent="false" value="[7.159,7.43)" label="7.16 – 7.43" />
  <ColorMapEntry rgb="69,31,179" transparent="false" value="[7.43,7.711)" label="7.43 – 7.71" />
  <ColorMapEntry rgb="66,34,181" transparent="false" value="[7.711,8.003)" label="7.71 – 8.00" />
  <ColorMapEntry rgb="64,37,184" transparent="false" value="[8.003,8.305)" label="8.00 – 8.30" />
  <ColorMapEntry rgb="61,40,186" transparent="false" value="[8.305,8.62)" label="8.30 – 8.62" />
  <ColorMapEntry rgb="59,44,189" transparent="false" value="[8.62,8.946)" label="8.62 – 8.95" />
  <ColorMapEntry rgb="57,47,192" transparent="false" value="[8.946,9.284)" label="8.95 – 9.28" />
  <ColorMapEntry rgb="54,50,194" transparent="false" value="[9.284,9.635)" label="9.28 – 9.63" />
  <ColorMapEntry rgb="52,53,197" transparent="false" value="[9.635,10)" label="9.63 – 10.00" />
  <ColorMapEntry rgb="50,56,200" transparent="false" value="[10,10.378)" label="10.00 – 10.38" />
  <ColorMapEntry rgb="47,59,202" transparent="false" value="[10.378,10.771)" label="10.38 – 10.77" />
  <ColorMapEntry rgb="45,62,205" transparent="false" value="[10.771,11.179)" label="10.77 – 11.18" />
  <ColorMapEntry rgb="42,66,207" transparent="false" value="[11.179,11.602)" label="11.18 – 11.60" />
  <ColorMapEntry rgb="40,69,210" transparent="false" value="[11.602,12.041)" label="11.60 – 12.04" />
  <ColorMapEntry rgb="38,72,213" transparent="false" value="[12.041,12.496)" label="12.04 – 12.50" />
  <ColorMapEntry rgb="35,75,215" transparent="false" value="[12.496,12.969)" label="12.50 – 12.97" />
  <ColorMapEntry rgb="33,78,218" transparent="false" value="[12.969,13.46)" label="12.97 – 13.46" />
  <ColorMapEntry rgb="30,81,220" transparent="false" value="[13.46,13.969)" label="13.46 – 13.97" />
  <ColorMapEntry rgb="28,85,223" transparent="false" value="[13.969,14.497)" label="13.97 – 14.50" />
  <ColorMapEntry rgb="26,88,226" transparent="false" value="[14.497,15.046)" label="14.50 – 15.05" />
  <ColorMapEntry rgb="23,91,228" transparent="false" value="[15.046,15.615)" label="15.05 – 15.62" />
  <ColorMapEntry rgb="21,94,231" transparent="false" value="[15.615,16.206)" label="15.62 – 16.21" />
  <ColorMapEntry rgb="19,97,234" transparent="false" value="[16.206,16.819)" label="16.21 – 16.82" />
  <ColorMapEntry rgb="16,100,236" transparent="false" value="[16.819,17.456)" label="16.82 – 17.46" />
  <ColorMapEntry rgb="14,103,239" transparent="false" value="[17.456,18.116)" label="17.46 – 18.12" />
  <ColorMapEntry rgb="11,107,241" transparent="false" value="[18.116,18.802)" label="18.12 – 18.80" />
  <ColorMapEntry rgb="9,110,244" transparent="false" value="[18.802,19.513)" label="18.80 – 19.51" />
  <ColorMapEntry rgb="7,113,247" transparent="false" value="[19.513,20.251)" label="19.51 – 20.25" />
  <ColorMapEntry rgb="4,116,249" transparent="false" value="[20.251,21.018)" label="20.25 – 21.02" />
  <ColorMapEntry rgb="2,119,252" transparent="false" value="[21.018,21.813)" label="21.02 – 21.81" />
  <ColorMapEntry rgb="0,122,254" transparent="false" value="[21.813,22.638)" label="21.81 – 22.64" />
  <ColorMapEntry rgb="0,125,248" transparent="false" value="[22.638,23.495)" label="22.64 – 23.50" />
  <ColorMapEntry rgb="0,129,242" transparent="false" value="[23.495,24.384)" label="23.50 – 24.38" />
  <ColorMapEntry rgb="0,132,236" transparent="false" value="[24.384,25.306)" label="24.38 – 25.31" />
  <ColorMapEntry rgb="0,135,230" transparent="false" value="[25.306,26.264)" label="25.31 – 26.26" />
  <ColorMapEntry rgb="0,138,224" transparent="false" value="[26.264,27.258)" label="26.26 – 27.26" />
  <ColorMapEntry rgb="0,141,218" transparent="false" value="[27.258,28.289)" label="27.26 – 28.29" />
  <ColorMapEntry rgb="0,144,212" transparent="false" value="[28.289,29.359)" label="28.29 – 29.36" />
  <ColorMapEntry rgb="0,147,206" transparent="false" value="[29.359,30.47)" label="29.36 – 30.47" />
  <ColorMapEntry rgb="0,151,200" transparent="false" value="[30.47,31.623)" label="30.47 – 31.62" />
  <ColorMapEntry rgb="0,154,194" transparent="false" value="[31.623,32.819)" label="31.62 – 32.82" />
  <ColorMapEntry rgb="0,157,188" transparent="false" value="[32.819,34.061)" label="32.82 – 34.06" />
  <ColorMapEntry rgb="0,160,182" transparent="false" value="[34.061,35.35)" label="34.06 – 35.35" />
  <ColorMapEntry rgb="0,163,176" transparent="false" value="[35.35,36.688)" label="35.35 – 36.69" />
  <ColorMapEntry rgb="0,166,170" transparent="false" value="[36.688,38.076)" label="36.69 – 38.08" />
  <ColorMapEntry rgb="0,170,163" transparent="false" value="[38.076,39.516)" label="38.08 – 39.52" />
  <ColorMapEntry rgb="0,173,157" transparent="false" value="[39.516,41.012)" label="39.52 – 41.01" />
  <ColorMapEntry rgb="0,176,151" transparent="false" value="[41.012,42.563)" label="41.01 – 42.56" />
  <ColorMapEntry rgb="0,179,145" transparent="false" value="[42.563,44.174)" label="42.56 – 44.17" />
  <ColorMapEntry rgb="0,182,139" transparent="false" value="[44.174,45.845)" label="44.17 – 45.84" />
  <ColorMapEntry rgb="0,185,133" transparent="false" value="[45.845,47.58)" label="45.84 – 47.58" />
  <ColorMapEntry rgb="0,188,127" transparent="false" value="[47.58,49.38)" label="47.58 – 49.38" />
  <ColorMapEntry rgb="0,192,121" transparent="false" value="[49.38,51.248)" label="49.38 – 51.25" />
  <ColorMapEntry rgb="0,195,115" transparent="false" value="[51.248,53.188)" label="51.25 – 53.19" />
  <ColorMapEntry rgb="0,198,109" transparent="false" value="[53.188,55.2)" label="53.19 – 55.20" />
  <ColorMapEntry rgb="0,201,103" transparent="false" value="[55.2,57.289)" label="55.20 – 57.29" />
  <ColorMapEntry rgb="0,204,97" transparent="false" value="[57.289,59.456)" label="57.29 – 59.46" />
  <ColorMapEntry rgb="0,207,91" transparent="false" value="[59.456,61.706)" label="59.46 – 61.71" />
  <ColorMapEntry rgb="0,210,85" transparent="false" value="[61.706,64.041)" label="61.71 – 64.04" />
  <ColorMapEntry rgb="0,214,78" transparent="false" value="[64.041,66.464)" label="64.04 – 66.46" />
  <ColorMapEntry rgb="0,217,72" transparent="false" value="[66.464,68.978)" label="66.46 – 68.98" />
  <ColorMapEntry rgb="0,220,66" transparent="false" value="[68.978,71.588)" label="68.98 – 71.59" />
  <ColorMapEntry rgb="0,223,60" transparent="false" value="[71.588,74.297)" label="71.59 – 74.30" />
  <ColorMapEntry rgb="0,226,54" transparent="false" value="[74.297,77.108)" label="74.30 – 77.11" />
  <ColorMapEntry rgb="0,229,48" transparent="false" value="[77.108,80.026)" label="77.11 – 80.03" />
  <ColorMapEntry rgb="0,232,42" transparent="false" value="[80.026,83.054)" label="80.03 – 83.05" />
  <ColorMapEntry rgb="0,236,36" transparent="false" value="[83.054,86.196)" label="83.05 – 86.20" />
  <ColorMapEntry rgb="0,239,30" transparent="false" value="[86.196,89.457)" label="86.20 – 89.46" />
  <ColorMapEntry rgb="0,242,24" transparent="false" value="[89.457,92.842)" label="89.46 – 92.84" />
  <ColorMapEntry rgb="0,245,18" transparent="false" value="[92.842,96.355)" label="92.84 – 96.36" />
  <ColorMapEntry rgb="0,248,12" transparent="false" value="[96.355,100.001)" label="96.36 – 100.00" />
  <ColorMapEntry rgb="0,255,0" transparent="false" value="[100.001,150.000]" label="100.00 – 150.00" />
  <ColorMapEntry rgb="255,255,0" transparent="false" value="[0.01,1.0)" label="0.01 – 1.00" />
  <ColorMapEntry rgb="255,255,4" transparent="false" value="[1,1.038)" label="1.00 – 1.04" />
  <ColorMapEntry rgb="255,255,8" transparent="false" value="[1.038,1.077)" label="1.04 – 1.08" />
  <ColorMapEntry rgb="255,255,12" transparent="false" value="[1.077,1.118)" label="1.08 – 1.12" />
  <ColorMapEntry rgb="255,255,17" transparent="false" value="[1.118,1.16)" label="1.12 – 1.16" />
  <ColorMapEntry rgb="255,255,21" transparent="false" value="[1.16,1.204)" label="1.16 – 1.20" />
  <ColorMapEntry rgb="255,255,25" transparent="false" value="[1.204,1.25)" label="1.20 – 1.25" />
  <ColorMapEntry rgb="255,255,30" transparent="false" value="[1.25,1.297)" label="1.25 – 1.30" />
  <ColorMapEntry rgb="255,255,34" transparent="false" value="[1.297,1.346)" label="1.30 – 1.35" />
  <ColorMapEntry rgb="255,255,38" transparent="false" value="[1.346,1.397)" label="1.35 – 1.40" />
  <ColorMapEntry rgb="255,255,42" transparent="false" value="[1.397,1.45)" label="1.40 – 1.45" />
  <ColorMapEntry rgb="255,255,47" transparent="false" value="[1.45,1.505)" label="1.45 – 1.50" />
  <ColorMapEntry rgb="255,255,51" transparent="false" value="[1.505,1.562)" label="1.50 – 1.56" />
  <ColorMapEntry rgb="255,255,55" transparent="false" value="[1.562,1.621)" label="1.56 – 1.62" />
  <ColorMapEntry rgb="255,255,60" transparent="false" value="[1.621,1.682)" label="1.62 – 1.68" />
  <ColorMapEntry rgb="255,255,64" transparent="false" value="[1.682,1.746)" label="1.68 – 1.75" />
  <ColorMapEntry rgb="255,255,68" transparent="false" value="[1.746,1.812)" label="1.75 – 1.81" />
  <ColorMapEntry rgb="255,255,72" transparent="false" value="[1.812,1.88)" label="1.81 – 1.88" />
  <ColorMapEntry rgb="255,255,77" transparent="false" value="[1.88,1.951)" label="1.88 – 1.95" />
  <ColorMapEntry rgb="255,255,81" transparent="false" value="[1.951,2.025)" label="1.95 – 2.02" />
  <ColorMapEntry rgb="255,255,85" transparent="false" value="[2.025,2.102)" label="2.02 – 2.10" />
  <ColorMapEntry rgb="255,255,90" transparent="false" value="[2.102,2.181)" label="2.10 – 2.18" />
  <ColorMapEntry rgb="255,255,94" transparent="false" value="[2.181,2.264)" label="2.18 – 2.26" />
  <ColorMapEntry rgb="255,255,98" transparent="false" value="[2.264,2.349)" label="2.26 – 2.35" />
  <ColorMapEntry rgb="255,255,102" transparent="false" value="[2.349,2.438)" label="2.35 – 2.44" />
  <ColorMapEntry rgb="255,255,107" transparent="false" value="[2.438,2.531)" label="2.44 – 2.53" />
  <ColorMapEntry rgb="255,255,111" transparent="false" value="[2.531,2.626)" label="2.53 – 2.63" />
  <ColorMapEntry rgb="255,255,115" transparent="false" value="[2.626,2.726)" label="2.63 – 2.73" />
  <ColorMapEntry rgb="255,255,120" transparent="false" value="[2.726,2.829)" label="2.73 – 2.83" />
  <ColorMapEntry rgb="255,255,124" transparent="false" value="[2.829,2.936)" label="2.83 – 2.94" />
  <ColorMapEntry rgb="255,255,128" transparent="false" value="[2.936,3.047)" label="2.94 – 3.05" />
  <ColorMapEntry rgb="255,255,132" transparent="false" value="[3.047,3.162)" label="3.05 – 3.16" />
  <ColorMapEntry rgb="255,255,137" transparent="false" value="[3.162,3.282)" label="3.16 – 3.28" />
  <ColorMapEntry rgb="255,255,141" transparent="false" value="[3.282,3.406)" label="3.28 – 3.41" />
  <ColorMapEntry rgb="255,255,145" transparent="false" value="[3.406,3.535)" label="3.41 – 3.54" />
  <ColorMapEntry rgb="255,255,150" transparent="false" value="[3.535,3.669)" label="3.54 – 3.67" />
  <ColorMapEntry rgb="255,255,154" transparent="false" value="[3.669,3.808)" label="3.67 – 3.81" />
  <ColorMapEntry rgb="255,255,158" transparent="false" value="[3.808,3.952)" label="3.81 – 3.95" />
  <ColorMapEntry rgb="255,255,162" transparent="false" value="[3.952,4.101)" label="3.95 – 4.10" />
  <ColorMapEntry rgb="255,255,167" transparent="false" value="[4.101,4.256)" label="4.10 – 4.26" />
  <ColorMapEntry rgb="255,255,171" transparent="false" value="[4.256,4.417)" label="4.26 – 4.42" />
  <ColorMapEntry rgb="255,255,175" transparent="false" value="[4.417,4.584)" label="4.42 – 4.58" />
  <ColorMapEntry rgb="255,255,180" transparent="false" value="[4.584,4.758)" label="4.58 – 4.76" />
  <ColorMapEntry rgb="255,255,181" transparent="false" value="[4.758,4.938)" label="4.76 – 4.94" />
  <ColorMapEntry rgb="255,250,180" transparent="false" value="[4.938,5.125)" label="4.94 – 5.12" />
  <ColorMapEntry rgb="255,245,180" transparent="false" value="[5.125,5.319)" label="5.12 – 5.32" />
  <ColorMapEntry rgb="255,240,180" transparent="false" value="[5.319,5.52)" label="5.32 – 5.52" />
  <ColorMapEntry rgb="255,235,180" transparent="false" value="[5.52,5.729)" label="5.52 – 5.73" />
  <ColorMapEntry rgb="255,230,180" transparent="false" value="[5.729,5.946)" label="5.73 – 5.95" />
  <ColorMapEntry rgb="255,230,181" transparent="false" value="[5.946,6.171)" label="5.95 – 6.17" />
  <ColorMapEntry rgb="255,227,174" transparent="false" value="[6.171,6.404)" label="6.17 – 6.40" />
  <ColorMapEntry rgb="255,224,169" transparent="false" value="[6.404,6.646)" label="6.40 – 6.65" />
  <ColorMapEntry rgb="255,221,164" transparent="false" value="[6.646,6.898)" label="6.65 – 6.90" />
  <ColorMapEntry rgb="255,218,159" transparent="false" value="[6.898,7.159)" label="6.90 – 7.16" />
  <ColorMapEntry rgb="255,216,154" transparent="false" value="[7.159,7.43)" label="7.16 – 7.43" />
  <ColorMapEntry rgb="255,213,149" transparent="false" value="[7.43,7.711)" label="7.43 – 7.71" />
  <ColorMapEntry rgb="255,210,144" transparent="false" value="[7.711,8.003)" label="7.71 – 8.00" />
  <ColorMapEntry rgb="255,207,138" transparent="false" value="[8.003,8.305)" label="8.00 – 8.30" />
  <ColorMapEntry rgb="255,205,133" transparent="false" value="[8.305,8.62)" label="8.30 – 8.62" />
  <ColorMapEntry rgb="255,202,128" transparent="false" value="[8.62,8.946)" label="8.62 – 8.95" />
  <ColorMapEntry rgb="255,199,123" transparent="false" value="[8.946,9.284)" label="8.95 – 9.28" />
  <ColorMapEntry rgb="255,196,118" transparent="false" value="[9.284,9.635)" label="9.28 – 9.63" />
  <ColorMapEntry rgb="255,193,113" transparent="false" value="[9.635,10)" label="9.63 – 10.00" />
  <ColorMapEntry rgb="255,191,108" transparent="false" value="[10,10.378)" label="10.00 – 10.38" />
  <ColorMapEntry rgb="255,188,102" transparent="false" value="[10.378,10.771)" label="10.38 – 10.77" />
  <ColorMapEntry rgb="255,185,97" transparent="false" value="[10.771,11.179)" label="10.77 – 11.18" />
  <ColorMapEntry rgb="255,182,92" transparent="false" value="[11.179,11.602)" label="11.18 – 11.60" />
  <ColorMapEntry rgb="255,180,87" transparent="false" value="[11.602,12.041)" label="11.60 – 12.04" />
  <ColorMapEntry rgb="255,177,82" transparent="false" value="[12.041,12.496)" label="12.04 – 12.50" />
  <ColorMapEntry rgb="255,174,77" transparent="false" value="[12.496,12.969)" label="12.50 – 12.97" />
  <ColorMapEntry rgb="255,171,72" transparent="false" value="[12.969,13.46)" label="12.97 – 13.46" />
  <ColorMapEntry rgb="255,169,66" transparent="false" value="[13.46,13.969)" label="13.46 – 13.97" />
  <ColorMapEntry rgb="255,166,61" transparent="false" value="[13.969,14.497)" label="13.97 – 14.50" />
  <ColorMapEntry rgb="255,163,56" transparent="false" value="[14.497,15.046)" label="14.50 – 15.05" />
  <ColorMapEntry rgb="255,160,51" transparent="false" value="[15.046,15.615)" label="15.05 – 15.62" />
  <ColorMapEntry rgb="255,157,46" transparent="false" value="[15.615,16.206)" label="15.62 – 16.21" />
  <ColorMapEntry rgb="255,155,41" transparent="false" value="[16.206,16.819)" label="16.21 – 16.82" />
  <ColorMapEntry rgb="255,152,36" transparent="false" value="[16.819,17.456)" label="16.82 – 17.46" />
  <ColorMapEntry rgb="255,149,30" transparent="false" value="[17.456,18.116)" label="17.46 – 18.12" />
  <ColorMapEntry rgb="255,146,25" transparent="false" value="[18.116,18.802)" label="18.12 – 18.80" />
  <ColorMapEntry rgb="255,144,20" transparent="false" value="[18.802,19.513)" label="18.80 – 19.51" />
  <ColorMapEntry rgb="255,141,15" transparent="false" value="[19.513,20.251)" label="19.51 – 20.25" />
  <ColorMapEntry rgb="255,138,10" transparent="false" value="[20.251,21.018)" label="20.25 – 21.02" />
  <ColorMapEntry rgb="255,135,5" transparent="false" value="[21.018,21.813)" label="21.02 – 21.81" />
  <ColorMapEntry rgb="255,133,2" transparent="false" value="[21.813,22.638)" label="21.81 – 22.64" />
  <ColorMapEntry rgb="255,133,0" transparent="false" value="[22.638,23.495)" label="22.64 – 23.50" />
  <ColorMapEntry rgb="255,125,0" transparent="false" value="[23.495,24.384)" label="23.50 – 24.38" />
  <ColorMapEntry rgb="255,118,0" transparent="false" value="[24.384,25.306)" label="24.38 – 25.31" />
  <ColorMapEntry rgb="255,110,0" transparent="false" value="[25.306,26.264)" label="25.31 – 26.26" />
  <ColorMapEntry rgb="255,103,0" transparent="false" value="[26.264,27.258)" label="26.26 – 27.26" />
  <ColorMapEntry rgb="255,96,0" transparent="false" value="[27.258,28.289)" label="27.26 – 28.29" />
  <ColorMapEntry rgb="255,88,0" transparent="false" value="[28.289,29.359)" label="28.29 – 29.36" />
  <ColorMapEntry rgb="255,81,0" transparent="false" value="[29.359,30.47)" label="29.36 – 30.47" />
  <ColorMapEntry rgb="255,73,0" transparent="false" value="[30.47,31.623)" label="30.47 – 31.62" />
  <ColorMapEntry rgb="255,66,0" transparent="false" value="[31.623,32.819)" label="31.62 – 32.82" />
  <ColorMapEntry rgb="255,59,0" transparent="false" value="[32.819,34.061)" label="32.82 – 34.06" />
  <ColorMapEntry rgb="255,51,0" transparent="false" value="[34.061,35.35)" label="34.06 – 35.35" />
  <ColorMapEntry rgb="255,44,0" transparent="false" value="[35.35,36.688)" label="35.35 – 36.69" />
  <ColorMapEntry rgb="255,36,0" transparent="false" value="[36.688,38.076)" label="36.69 – 38.08" />
  <ColorMapEntry rgb="255,29,0" transparent="false" value="[38.076,39.516)" label="38.08 – 39.52" />
  <ColorMapEntry rgb="255,22,0" transparent="false" value="[39.516,41.012)" label="39.52 – 41.01" />
  <ColorMapEntry rgb="255,14,0" transparent="false" value="[41.012,42.563)" label="41.01 – 42.56" />
  <ColorMapEntry rgb="255,7,0" transparent="false" value="[42.563,44.174)" label="42.56 – 44.17" />
  <ColorMapEntry rgb="255,3,0" transparent="false" value="[44.174,45.845)" label="44.17 – 45.84" />
  <ColorMapEntry rgb="255,0,0" transparent="false" value="[45.845,47.58)" label="45.84 – 47.58" />
  <ColorMapEntry rgb="249,0,0" transparent="false" value="[47.58,49.38)" label="47.58 – 49.38" />
  <ColorMapEntry rgb="243,0,0" transparent="false" value="[49.38,51.248)" label="49.38 – 51.25" />
  <ColorMapEntry rgb="237,0,0" transparent="false" value="[51.248,53.188)" label="51.25 – 53.19" />
  <ColorMapEntry rgb="232,0,0" transparent="false" value="[53.188,55.2)" label="53.19 – 55.20" />
  <ColorMapEntry rgb="226,0,0" transparent="false" value="[55.2,57.289)" label="55.20 – 57.29" />
  <ColorMapEntry rgb="220,0,0" transparent="false" value="[57.289,59.456)" label="57.29 – 59.46" />
  <ColorMapEntry rgb="215,0,0" transparent="false" value="[59.456,61.706)" label="59.46 – 61.71" />
  <ColorMapEntry rgb="209,0,0" transparent="false" value="[61.706,64.041)" label="61.71 – 64.04" />
  <ColorMapEntry rgb="203,0,0" transparent="false" value="[64.041,66.464)" label="64.04 – 66.46" />
  <ColorMapEntry rgb="198,0,0" transparent="false" value="[66.464,68.978)" label="66.46 – 68.98" />
  <ColorMapEntry rgb="192,0,0" transparent="false" value="[68.978,71.588)" label="68.98 – 71.59" />
  <ColorMapEntry rgb="186,0,0" transparent="false" value="[71.588,74.297)" label="71.59 – 74.30" />
  <ColorMapEntry rgb="181,0,0" transparent="false" value="[74.297,77.108)" label="74.30 – 77.11" />
  <ColorMapEntry rgb="175,0,0" transparent="false" value="[77.108,80.026)" label="77.11 – 80.03" />
  <ColorMapEntry rgb="169,0,0" transparent="false" value="[80.026,83.054)" label="80.03 – 83.05" />
  <ColorMapEntry rgb="164,0,0" transparent="false" value="[83.054,86.196)" label="83.05 – 86.20" />
  <ColorMapEntry rgb="158,0,0" transparent="false" value="[86.196,89.457)" label="86.20 – 89.46" />
  <ColorMapEntry rgb="152,0,0" transparent="false" value="[89.457,92.842)" label="89.46 – 92.84" />
  <ColorMapEntry rgb="147,0,0" transparent="false" value="[92.842,96.355)" label="92.84 – 96.36" />
  <ColorMapEntry rgb="141,0,0" transparent="false" value="[96.355,100.001)" label="96.36 – 100.00" />
  <ColorMapEntry rgb="135,0,0" transparent="false" value="[100.001,150.000]" label="100.00 – 150.00" />
</ColorMap>