<?xml version="1.0" encoding="UTF-8"?>
<ColorMap xmlns:xsi="http://www.w3.org/2001/XMLSchema-instance"
          xsi:noNamespaceSchemaLocation="http://map1.vis.earthdata.nasa.gov/schema/ColorMap_v1.0.xsd"
          units="">
  <ColorMapEntry rgb="255,255,255" transparent="true" label="No Data" />
  <ColorMapEntry rgb="0,0,0" transparent="true" label="Unknown 1" />
  <ColorMapEntry rgb="227,26,28" transparent="true" label="Unknown 2" />
  <ColorMapEntry rgb="51,160,44" transparent="true" label="Unknown 3" />
  <ColorMapEntry rgb="31,120,180" transparent="true" label="Unknown 4" />
  <ColorMapEntry rgb="255,127,255" transparent="true" label="Unknown 5" />
  <ColorMapEntry rgb="106,61,154" transparent="true" label="Unknown 6" />
  <ColorMapEntry rgb="251,154,153" transparent="true" label="Unknown 7" />
  <ColorMapEntry rgb="178,223,138" transparent="true" label="Unknown 8" />
  <ColorMapEntry rgb="156,216,217" transparent="true" label="Unknown 9" />
  <ColorMapEntry rgb="253,191,111" transparent="true" label="Unknown 10" />
  <ColorMapEntry rgb="202,178,214" transparent="true" label="Unknown 11" />
  <ColorMapEntry rgb="90,90,90" transparent="true" label="Unknown 12" />
  <ColorMapEntry rgb="150,150,150" transparent="true" label="Unknown 13" />
  <ColorMapEntry rgb="188,188,188" transparent="true" label="Unknown 14" />
  <ColorMapEntry rgb="220,220,220" transparent="true" label="Unknown 15" />
  <ColorMapEntry rgb="240,240,240" transparent="true" label="Unknown 16" />
  <ColorMapEntry rgb="255,255,255" transparent="true" label="Unknown 17" />
  <ColorMapEntry rgb="255,253,253" transparent="true" label="Unknown 18" />
  <ColorMapEntry rgb="255,252,252" transparent="true" label="Unknown 19" />
  <ColorMapEntry rgb="255,251,251" transparent="true" label="Unknown 20" />
  <ColorMapEntry rgb="255,250,250" transparent="true" label="Unknown 21" />
  <ColorMapEntry rgb="255,248,248" transparent="true" label="Unknown 22" />
  <ColorMapEntry rgb="247,255,250" transparent="true" label="Unknown 23" />
  <ColorMapEntry rgb="255,246,247" transparent="true" label="Unknown 24" />
  <ColorMapEntry rgb="255,245,246" transparent="true" label="Unknown 25" />
  <ColorMapEntry rgb="255,243,245" transparent="true" label="Unknown 26" />
  <ColorMapEntry rgb="255,242,245" transparent="true" label="Unknown 27" />
  <ColorMapEntry rgb="255,241,244" transparent="true" label="Unknown 28" />
  <ColorMapEntry rgb="255,239,243" transparent="true" label="Unknown 29" />
  <ColorMapEntry rgb="255,238,243" transparent="true" label="Unknown 30" />
  <ColorMapEntry rgb="255,237,243" transparent="true" label="Unknown 31" />
  <ColorMapEntry rgb="255,236,243" transparent="true" label="Unknown 32" />
  <ColorMapEntry rgb="255,234,242" transparent="true" label="Unknown 33" />
  <ColorMapEntry rgb="255,233,242" transparent="true" label="Unknown 34" />
  <ColorMapEntry rgb="255,232,242" transparent="true" label="Unknown 35" />
  <ColorMapEntry rgb="255,230,242" transparent="true" label="Unknown 36" />
  <ColorMapEntry rgb="255,229,242" transparent="true" label="Unknown 37" />
  <ColorMapEntry rgb="255,228,243" transparent="true" label="Unknown 38" />
  <ColorMapEntry rgb="255,227,243" transparent="true" label="Unknown 39" />
  <ColorMapEntry rgb="255,225,243" transparent="true" label="Unknown 40" />
  <ColorMapEntry rgb="255,224,244" transparent="true" label="Unknown 41" />
  <ColorMapEntry rgb="255,223,244" transparent="true" label="Unknown 42" />
  <ColorMapEntry rgb="255,222,246" transparent="true" label="Unknown 43" />
  <ColorMapEntry rgb="255,220,246" transparent="true" label="Unknown 44" />
  <ColorMapEntry rgb="255,219,246" transparent="true" label="Unknown 45" />
  <ColorMapEntry rgb="255,218,247" transparent="true" label="Unknown 46" />
  <ColorMapEntry rgb="255,216,249" transparent="true" label="Unknown 47" />
  <ColorMapEntry rgb="255,215,249" transparent="true" label="Unknown 48" />
  <ColorMapEntry rgb="255,214,250" transparent="true" label="Unknown 49" />
  <ColorMapEntry rgb="255,213,251" transparent="true" label="Unknown 50" />
  <ColorMapEntry rgb="255,211,253" transparent="true" label="Unknown 51" />
  <ColorMapEntry rgb="254,210,255" transparent="true" label="Unknown 52" />
  <ColorMapEntry rgb="253,209,255" transparent="true" label="Unknown 53" />
  <ColorMapEntry rgb="251,207,255" transparent="true" label="Unknown 54" />
  <ColorMapEntry rgb="250,206,255" transparent="true" label="Unknown 55" />
  <ColorMapEntry rgb="248,205,255" transparent="true" label="Unknown 56" />
  <ColorMapEntry rgb="247,204,255" transparent="true" label="Unknown 57" />
  <ColorMapEntry rgb="245,202,255" transparent="true" label="Unknown 58" />
  <ColorMapEntry rgb="243,201,255" transparent="true" label="Unknown 59" />
  <ColorMapEntry rgb="241,200,255" transparent="true" label="Unknown 60" />
  <ColorMapEntry rgb="239,198,255" transparent="true" label="Unknown 61" />
  <ColorMapEntry rgb="237,197,255" transparent="true" label="Unknown 62" />
  <ColorMapEntry rgb="235,196,255" transparent="true" label="Unknown 63" />
  <ColorMapEntry rgb="233,195,255" transparent="true" label="Unknown 64" />
  <ColorMapEntry rgb="230,193,255" transparent="true" label="Unknown 65" />
  <ColorMapEntry rgb="229,192,255" transparent="true" label="Unknown 66" />
  <ColorMapEntry rgb="226,191,255" transparent="true" label="Unknown 67" />
  <ColorMapEntry rgb="224,190,255" transparent="true" label="Unknown 68" />
  <ColorMapEntry rgb="221,188,255" transparent="true" label="Unknown 69" />
  <ColorMapEntry rgb="218,187,255" transparent="true" label="Unknown 70" />
  <ColorMapEntry rgb="216,186,255" transparent="true" label="Unknown 71" />
  <ColorMapEntry rgb="212,184,255" transparent="true" label="Unknown 72" />
  <ColorMapEntry rgb="210,183,255" transparent="true" label="Unknown 73" />
  <ColorMapEntry rgb="207,182,255" transparent="true" label="Unknown 74" />
  <ColorMapEntry rgb="204,181,255" transparent="true" label="Unknown 75" />
  <ColorMapEntry rgb="201,179,255" transparent="true" label="Unknown 76" />
  <ColorMapEntry rgb="197,178,255" transparent="true" label="Unknown 77" />
  <ColorMapEntry rgb="194,177,255" transparent="true" label="Unknown 78" />
  <ColorMapEntry rgb="191,175,255" transparent="true" label="Unknown 79" />
  <ColorMapEntry rgb="188,174,255" transparent="true" label="Unknown 80" />
  <ColorMapEntry rgb="185,173,255" transparent="true" label="Unknown 81" />
  <ColorMapEntry rgb="181,172,255" transparent="true" label="Unknown 82" />
  <ColorMapEntry rgb="177,170,255" transparent="true" label="Unknown 83" />
  <ColorMapEntry rgb="173,169,255" transparent="true" label="Unknown 84" />
  <ColorMapEntry rgb="170,169,255" transparent="true" label="Unknown 85" />
  <ColorMapEntry rgb="167,169,255" transparent="true" label="Unknown 86" />
  <ColorMapEntry rgb="166,170,255" transparent="true" label="Unknown 87" />
  <ColorMapEntry rgb="165,171,255" transparent="true" label="Unknown 88" />
  <ColorMapEntry rgb="164,172,255" transparent="true" label="Unknown 89" />
  <ColorMapEntry rgb="162,174,255" transparent="true" label="Unknown 90" />
  <ColorMapEntry rgb="161,176,255" transparent="true" label="Unknown 91" />
  <ColorMapEntry rgb="160,177,255" transparent="true" label="Unknown 92" />
  <ColorMapEntry rgb="159,180,255" transparent="true" label="Unknown 93" />
  <ColorMapEntry rgb="157,181,255" transparent="true" label="Unknown 94" />
  <ColorMapEntry rgb="156,183,255" transparent="true" label="Unknown 95" />
  <ColorMapEntry rgb="155,185,255" transparent="true" label="Unknown 96" />
  <ColorMapEntry rgb="153,188,255" transparent="true" label="Unknown 97" />
  <ColorMapEntry rgb="152,189,255" transparent="true" label="Unknown 98" />
  <ColorMapEntry rgb="151,192,255" transparent="true" label="Unknown 99" />
  <ColorMapEntry rgb="150,194,255" transparent="true" label="Unknown 100" />
  <ColorMapEntry rgb="148,197,255" transparent="true" label="Unknown 101" />
  <ColorMapEntry rgb="147,200,255" transparent="true" label="Unknown 102" />
  <ColorMapEntry rgb="146,202,255" transparent="true" label="Unknown 103" />
  <ColorMapEntry rgb="144,205,255" transparent="true" label="Unknown 104" />
  <ColorMapEntry rgb="143,207,255" transparent="true" label="Unknown 105" />
  <ColorMapEntry rgb="142,210,255" transparent="true" label="Unknown 106" />
  <ColorMapEntry rgb="141,213,255" transparent="true" label="Unknown 107" />
  <ColorMapEntry rgb="139,216,255" transparent="true" label="Unknown 108" />
  <ColorMapEntry rgb="138,219,255" transparent="true" label="Unknown 109" />
  <ColorMapEntry rgb="137,222,255" transparent="true" label="Unknown 110" />
  <ColorMapEntry rgb="135,226,255" transparent="true" label="Unknown 111" />
  <ColorMapEntry rgb="134,228,255" transparent="true" label="Unknown 112" />
  <ColorMapEntry rgb="133,232,255" transparent="true" label="Unknown 113" />
  <ColorMapEntry rgb="132,235,255" transparent="true" label="Unknown 114" />
  <ColorMapEntry rgb="130,239,255" transparent="true" label="Unknown 115" />
  <ColorMapEntry rgb="129,242,255" transparent="true" label="Unknown 116" />
  <ColorMapEntry rgb="128,246,255" transparent="true" label="Unknown 117" />
  <ColorMapEntry rgb="127,250,255" transparent="true" label="Unknown 118" />
  <ColorMapEntry rgb="125,254,255" transparent="true" label="Unknown 119" />
  <ColorMapEntry rgb="124,255,251" transparent="true" label="Unknown 120" />
  <ColorMapEntry rgb="123,255,247" transparent="true" label="Unknown 121" />
  <ColorMapEntry rgb="121,255,243" transparent="true" label="Unknown 122" />
  <ColorMapEntry rgb="120,255,239" transparent="true" label="Unknown 123" />
  <ColorMapEntry rgb="119,255,234" transparent="true" label="Unknown 124" />
  <ColorMapEntry rgb="118,255,231" transparent="true" label="Unknown 125" />
  <ColorMapEntry rgb="116,255,226" transparent="true" label="Unknown 126" />
  <ColorMapEntry rgb="115,255,221" transparent="true" label="Unknown 127" />
  <ColorMapEntry rgb="114,255,217" transparent="false" value="1.10" label="1.10" />
  <ColorMapEntry rgb="112,255,212" transparent="false" value="1.11" label="1.11" />
  <ColorMapEntry rgb="111,255,208" transparent="false" value="1.12" label="1.12" />
  <ColorMapEntry rgb="110,255,204" transparent="false" value="1.13" label="1.13" />
  <ColorMapEntry rgb="109,255,199" transparent="false" value="1.14" label="1.14" />
  <ColorMapEntry rgb="107,255,194" transparent="false" value="1.15" label="1.15" />
  <ColorMapEntry rgb="106,255,189" transparent="false" value="1.16" label="1.16" />
  <ColorMapEntry rgb="105,255,183" transparent="false" value="1.17" label="1.17" />
  <ColorMapEntry rgb="103,255,178" transparent="false" value="1.18" label="1.18" />
  <ColorMapEntry rgb="102,255,173" transparent="false" value="1.19" label="1.19" />
  <ColorMapEntry rgb="101,255,168" transparent="false" value="1.20" label="1.20" />
  <ColorMapEntry rgb="100,255,163" transparent="false" value="1.21" label="1.21" />
  <ColorMapEntry rgb="98,255,158" transparent="false" value="1.22" label="1.22" />
  <ColorMapEntry rgb="97,255,152" transparent="false" value="1.23" label="1.23" />
  <ColorMapEntry rgb="96,255,147" transparent="false" value="1.24" label="1.24" />
  <ColorMapEntry rgb="95,255,142" transparent="false" value="1.25" label="1.25" />
  <ColorMapEntry rgb="93,255,135" transparent="false" value="1.26" label="1.26" />
  <ColorMapEntry rgb="92,255,130" transparent="false" value="1.27" label="1.27" />
  <ColorMapEntry rgb="91,255,124" transparent="false" value="1.28" label="1.28" />
  <ColorMapEntry rgb="89,255,118" transparent="false" value="1.29" label="1.29" />
  <ColorMapEntry rgb="88,255,112" transparent="false" value="1.30" label="1.30" />
  <ColorMapEntry rgb="87,255,106" transparent="false" value="1.31" label="1.31" />
  <ColorMapEntry rgb="86,255,100" transparent="false" value="1.32" label="1.32" />
  <ColorMapEntry rgb="85,255,93" transparent="false" value="1.33" label="1.33" />
  <ColorMapEntry rgb="84,255,87" transparent="false" value="1.34" label="1.34" />
  <ColorMapEntry rgb="83,255,83" transparent="false" value="1.35" label="1.35" />
  <ColorMapEntry rgb="88,255,81" transparent="false" value="1.36" label="1.36" />
  <ColorMapEntry rgb="92,255,80" transparent="false" value="1.37" label="1.37" />
  <ColorMapEntry rgb="95,255,79" transparent="false" value="1.38" label="1.38" />
  <ColorMapEntry rgb="99,255,78" transparent="false" value="1.39" label="1.39" />
  <ColorMapEntry rgb="103,255,76" transparent="false" value="1.40" label="1.40" />
  <ColorMapEntry rgb="108,255,75" transparent="false" value="1.41" label="1.41" />
  <ColorMapEntry rgb="113,255,74" transparent="false" value="1.42" label="1.42" />
  <ColorMapEntry rgb="117,255,72" transparent="false" value="1.43" label="1.43" />
  <ColorMapEntry rgb="121,255,71" transparent="false" value="1.44" label="1.44" />
  <ColorMapEntry rgb="126,255,70" transparent="false" value="1.45" label="1.45" />
  <ColorMapEntry rgb="130,255,69" transparent="false" value="1.46" label="1.46" />
  <ColorMapEntry rgb="135,255,67" transparent="false" value="1.47" label="1.47" />
  <ColorMapEntry rgb="140,255,66" transparent="false" value="1.48" label="1.48" />
  <ColorMapEntry rgb="145,255,65" transparent="false" value="1.49" label="1.49" />
  <ColorMapEntry rgb="150,255,64" transparent="false" value="1.50" label="1.50" />
  <ColorMapEntry rgb="155,255,62" transparent="false" value="1.51" label="1.51" />
  <ColorMapEntry rgb="160,255,61" transparent="false" value="1.52" label="1.52" />
  <ColorMapEntry rgb="165,255,60" transparent="false" value="1.53" label="1.53" />
  <ColorMapEntry rgb="170,255,58" transparent="false" value="1.54" label="1.54" />
  <ColorMapEntry rgb="175,255,57" transparent="false" value="1.56" label="1.56" />
  <ColorMapEntry rgb="181,255,56" transparent="false" value="1.57" label="1.57" />
  <ColorMapEntry rgb="186,255,55" transparent="false" value="1.58" label="1.58" />
  <ColorMapEntry rgb="192,255,53" transparent="false" value="1.59" label="1.59" />
  <ColorMapEntry rgb="198,255,52" transparent="false" value="1.60" label="1.60" />
  <ColorMapEntry rgb="203,255,51" transparent="false" value="1.61" label="1.61" />
  <ColorMapEntry rgb="209,255,49" transparent="false" value="1.62" label="1.62" />
  <ColorMapEntry rgb="215,255,48" transparent="false" value="1.63" label="1.63" />
  <ColorMapEntry rgb="221,255,47" transparent="false" value="1.64" label="1.64" />
  <ColorMapEntry rgb="227,255,46" transparent="false" value="1.65" label="1.65" />
  <ColorMapEntry rgb="233,255,44" transparent="false" value="1.66" label="1.66" />
  <ColorMapEntry rgb="239,255,43" transparent="false" value="1.67" label="1.67" />
  <ColorMapEntry rgb="245,255,42" transparent="false" value="1.68" label="1.68" />
  <ColorMapEntry rgb="252,255,40" transparent="false" value="1.69" label="1.69" />
  <ColorMapEntry rgb="255,250,39" transparent="false" value="1.70" label="1.70" />
  <ColorMapEntry rgb="255,244,38" transparent="false" value="1.71" label="1.71" />
  <ColorMapEntry rgb="255,237,37" transparent="false" value="1.72" label="1.72" />
  <ColorMapEntry rgb="255,231,35" transparent="false" value="1.73" label="1.73" />
  <ColorMapEntry rgb="255,223,34" transparent="false" value="1.74" label="1.74" />
  <ColorMapEntry rgb="255,217,33" transparent="false" value="1.75" label="1.75" />
  <ColorMapEntry rgb="255,211,32" transparent="false" value="1.76" label="1.76" />
  <ColorMapEntry rgb="255,203,30" transparent="false" value="1.77" label="1.77" />
  <ColorMapEntry rgb="255,196,29" transparent="false" value="1.78" label="1.78" />
  <ColorMapEntry rgb="255,189,28" transparent="false" value="1.79" label="1.79" />
  <ColorMapEntry rgb="255,182,26" transparent="false" value="1.80" label="1.80" />
  <ColorMapEntry rgb="255,175,25" transparent="false" value="1.81" label="1.81" />
  <ColorMapEntry rgb="255,167,24" transparent="false" value="1.82" label="1.82" />
  <ColorMapEntry rgb="255,160,23" transparent="false" value="1.83" label="1.83" />
  <ColorMapEntry rgb="255,153,21" transparent="false" value="1.84" label="1.84" />
  <ColorMapEntry rgb="255,145,20" transparent="false" value="1.85" label="1.85" />
  <ColorMapEntry rgb="255,138,19" transparent="false" value="1.86" label="1.86" />
  <ColorMapEntry rgb="255,130,17" transparent="false" value="1.87" label="1.87" />
  <ColorMapEntry rgb="255,122,16" transparent="false" value="1.88" label="1.88" />
  <ColorMapEntry rgb="255,115,15" transparent="false" value="1.89" label="1.89" />
  <ColorMapEntry rgb="255,107,14" transparent="false" value="1.90" label="1.90" />
  <ColorMapEntry rgb="255,98,12" transparent="false" value="1.91" label="1.91" />
  <ColorMapEntry rgb="255,91,11" transparent="false" value="1.92" label="1.92" />
  <ColorMapEntry rgb="255,82,12" transparent="false" value="1.93" label="1.93" />
  <ColorMapEntry rgb="255,74,8" transparent="false" value="1.94" label="1.94" />
  <ColorMapEntry rgb="255,66,7" transparent="false" value="1.95" label="1.95" />
  <ColorMapEntry rgb="255,58,6" transparent="false" value="1.96" label="1.96" />
  <ColorMapEntry rgb="255,49,5" transparent="false" value="1.97" label="1.97" />
  <ColorMapEntry rgb="255,41,3" transparent="false" value="1.98" label="1.98" />
  <ColorMapEntry rgb="255,32,2" transparent="false" value="1.99" label="1.99" />
  <ColorMapEntry rgb="255,29,2" transparent="false" value="2.0" label="2.00" />
</ColorMap>