<?xml version="1.0" encoding="UTF-8"?>
<ColorMaps xmlns:xsi="http://www.w3.org/2001/XMLSchema-instance"
    xsi:noNamespaceSchemaLocation="http://gibs.earthdata.nasa.gov/schemas/ColorMap_v1.2.xsd">
    
    <ColorMap title="No Data">
        <Entries>
            <ColorMapEntry rgb="0,0,0" transparent="true" label="No Data" nodata="true"/>
        </Entries>
    </ColorMap>
    
    <ColorMap title="Sea Surface Temperature" units="°C">
        <Entries minLabel="-2 °C" maxLabel="45 °C">
            <ColorMapEntry rgb="91,10,118" transparent="false" sourceValue="[-2,-1.82)" value="[-2,-1.82)" label="-2 - -1.82 °C" ref="1"  />
            <ColorMapEntry rgb="99,9,139" transparent="false" sourceValue="[-1.82,-1.63)" value="[-1.82,-1.63)" label="-1.82 - -1.63 °C" ref="2"  />
            <ColorMapEntry rgb="112,7,171" transparent="false" sourceValue="[-1.63,-1.45)" value="[-1.63,-1.45)" label="-1.63 - -1.45 °C" ref="3"  />
            <ColorMapEntry rgb="124,7,202" transparent="false" sourceValue="[-1.45,-1.26)" value="[-1.45,-1.26)" label="-1.45 - -1.26 °C" ref="4"  />
            <ColorMapEntry rgb="130,7,223" transparent="false" sourceValue="[-1.26,-1.08)" value="[-1.26,-1.08)" label="-1.26 - -1.08 °C" ref="5"  />
            <ColorMapEntry rgb="128,7,234" transparent="false" sourceValue="[-1.08,-0.89)" value="[-1.08,-0.89)" label="-1.08 - -0.89 °C" ref="6"  />
            <ColorMapEntry rgb="120,7,238" transparent="false" sourceValue="[-0.89,-0.71)" value="[-0.89,-0.71)" label="-0.89 - -0.71 °C" ref="7"  />
            <ColorMapEntry rgb="110,7,238" transparent="false" sourceValue="[-0.71,-0.53)" value="[-0.71,-0.53)" label="-0.71 - -0.53 °C" ref="8"  />
            <ColorMapEntry rgb="100,7,239" transparent="false" sourceValue="[-0.53,-0.34)" value="[-0.53,-0.34)" label="-0.53 - -0.34 °C" ref="9"  />
            <ColorMapEntry rgb="88,7,239" transparent="false" sourceValue="[-0.34,-0.16)" value="[-0.34,-0.16)" label="-0.34 - -0.16 °C" ref="10"  />
            <ColorMapEntry rgb="73,7,239" transparent="false" sourceValue="[-0.16,0.03)" value="[-0.16,0.03)" label="-0.16 - 0.03 °C" ref="11"  />
            <ColorMapEntry rgb="54,7,239" transparent="false" sourceValue="[0.03,0.21)" value="[0.03,0.21)" label="0.03 - 0.21 °C" ref="12"  />
            <ColorMapEntry rgb="34,8,238" transparent="false" sourceValue="[0.21,0.4)" value="[0.21,0.4)" label="0.21 - 0.4 °C" ref="13"  />
            <ColorMapEntry rgb="18,8,236" transparent="false" sourceValue="[0.4,0.58)" value="[0.4,0.58)" label="0.4 - 0.58 °C" ref="14"  />
            <ColorMapEntry rgb="11,8,233" transparent="false" sourceValue="[0.58,0.76)" value="[0.58,0.76)" label="0.58 - 0.76 °C" ref="15"  />
            <ColorMapEntry rgb="8,8,228" transparent="false" sourceValue="[0.76,0.95)" value="[0.76,0.95)" label="0.76 - 0.95 °C" ref="16"  />
            <ColorMapEntry rgb="8,8,224" transparent="false" sourceValue="[0.95,1.13)" value="[0.95,1.13)" label="0.95 - 1.13 °C" ref="17"  />
            <ColorMapEntry rgb="8,8,221" transparent="false" sourceValue="[1.13,1.32)" value="[1.13,1.32)" label="1.13 - 1.32 °C" ref="18"  />
            <ColorMapEntry rgb="8,8,217" transparent="false" sourceValue="[1.32,1.5)" value="[1.32,1.5)" label="1.32 - 1.5 °C" ref="19"  />
            <ColorMapEntry rgb="8,8,212" transparent="false" sourceValue="[1.5,1.69)" value="[1.5,1.69)" label="1.5 - 1.69 °C" ref="20"  />
            <ColorMapEntry rgb="8,8,207" transparent="false" sourceValue="[1.69,1.87)" value="[1.69,1.87)" label="1.69 - 1.87 °C" ref="21"  />
            <ColorMapEntry rgb="8,8,201" transparent="false" sourceValue="[1.87,2.05)" value="[1.87,2.05)" label="1.87 - 2.05 °C" ref="22"  />
            <ColorMapEntry rgb="8,8,196" transparent="false" sourceValue="[2.05,2.24)" value="[2.05,2.24)" label="2.05 - 2.24 °C" ref="23"  />
            <ColorMapEntry rgb="8,8,191" transparent="false" sourceValue="[2.24,2.42)" value="[2.24,2.42)" label="2.24 - 2.42 °C" ref="24"  />
            <ColorMapEntry rgb="8,8,185" transparent="false" sourceValue="[2.42,2.61)" value="[2.42,2.61)" label="2.42 - 2.61 °C" ref="25"  />
            <ColorMapEntry rgb="8,8,179" transparent="false" sourceValue="[2.61,2.79)" value="[2.61,2.79)" label="2.61 - 2.79 °C" ref="26"  />
            <ColorMapEntry rgb="8,8,173" transparent="false" sourceValue="[2.79,2.98)" value="[2.79,2.98)" label="2.79 - 2.98 °C" ref="27"  />
            <ColorMapEntry rgb="8,8,166" transparent="false" sourceValue="[2.98,3.16)" value="[2.98,3.16)" label="2.98 - 3.16 °C" ref="28"  />
            <ColorMapEntry rgb="8,8,159" transparent="false" sourceValue="[3.16,3.35)" value="[3.16,3.35)" label="3.16 - 3.35 °C" ref="29"  />
            <ColorMapEntry rgb="8,8,153" transparent="false" sourceValue="[3.35,3.53)" value="[3.35,3.53)" label="3.35 - 3.53 °C" ref="30"  />
            <ColorMapEntry rgb="8,11,147" transparent="false" sourceValue="[3.53,3.71)" value="[3.53,3.71)" label="3.53 - 3.71 °C" ref="31"  />
            <ColorMapEntry rgb="8,16,139" transparent="false" sourceValue="[3.71,3.9)" value="[3.71,3.9)" label="3.71 - 3.9 °C" ref="32"  />
            <ColorMapEntry rgb="8,23,130" transparent="false" sourceValue="[3.9,4.08)" value="[3.9,4.08)" label="3.9 - 4.08 °C" ref="33"  />
            <ColorMapEntry rgb="8,30,121" transparent="false" sourceValue="[4.08,4.27)" value="[4.08,4.27)" label="4.08 - 4.27 °C" ref="34"  />
            <ColorMapEntry rgb="8,38,114" transparent="false" sourceValue="[4.27,4.45)" value="[4.27,4.45)" label="4.27 - 4.45 °C" ref="35"  />
            <ColorMapEntry rgb="8,46,109" transparent="false" sourceValue="[4.45,4.64)" value="[4.45,4.64)" label="4.45 - 4.64 °C" ref="36"  />
            <ColorMapEntry rgb="8,54,106" transparent="false" sourceValue="[4.64,4.82)" value="[4.64,4.82)" label="4.64 - 4.82 °C" ref="37"  />
            <ColorMapEntry rgb="8,62,104" transparent="false" sourceValue="[4.82,5)" value="[4.82,5)" label="4.82 - 5 °C" ref="38"  />
            <ColorMapEntry rgb="8,70,104" transparent="false" sourceValue="[5,5.19)" value="[5,5.19)" label="5 - 5.19 °C" ref="39"  />
            <ColorMapEntry rgb="8,78,104" transparent="false" sourceValue="[5.19,5.37)" value="[5.19,5.37)" label="5.19 - 5.37 °C" ref="40"  />
            <ColorMapEntry rgb="8,86,106" transparent="false" sourceValue="[5.37,5.56)" value="[5.37,5.56)" label="5.37 - 5.56 °C" ref="41"  />
            <ColorMapEntry rgb="8,93,107" transparent="false" sourceValue="[5.56,5.74)" value="[5.56,5.74)" label="5.56 - 5.74 °C" ref="42"  />
            <ColorMapEntry rgb="8,98,109" transparent="false" sourceValue="[5.74,5.93)" value="[5.74,5.93)" label="5.74 - 5.93 °C" ref="43"  />
            <ColorMapEntry rgb="8,100,112" transparent="false" sourceValue="[5.93,6.11)" value="[5.93,6.11)" label="5.93 - 6.11 °C" ref="44"  />
            <ColorMapEntry rgb="8,99,114" transparent="false" sourceValue="[6.11,6.29)" value="[6.11,6.29)" label="6.11 - 6.29 °C" ref="45"  />
            <ColorMapEntry rgb="8,98,117" transparent="false" sourceValue="[6.29,6.48)" value="[6.29,6.48)" label="6.29 - 6.48 °C" ref="46"  />
            <ColorMapEntry rgb="8,97,122" transparent="false" sourceValue="[6.48,6.66)" value="[6.48,6.66)" label="6.48 - 6.66 °C" ref="47"  />
            <ColorMapEntry rgb="8,98,130" transparent="false" sourceValue="[6.66,6.85)" value="[6.66,6.85)" label="6.66 - 6.85 °C" ref="48"  />
            <ColorMapEntry rgb="8,101,139" transparent="false" sourceValue="[6.85,7.03)" value="[6.85,7.03)" label="6.85 - 7.03 °C" ref="49"  />
            <ColorMapEntry rgb="8,104,147" transparent="false" sourceValue="[7.03,7.22)" value="[7.03,7.22)" label="7.03 - 7.22 °C" ref="50"  />
            <ColorMapEntry rgb="8,108,152" transparent="false" sourceValue="[7.22,7.4)" value="[7.22,7.4)" label="7.22 - 7.4 °C" ref="51"  />
            <ColorMapEntry rgb="8,113,155" transparent="false" sourceValue="[7.4,7.58)" value="[7.4,7.58)" label="7.4 - 7.58 °C" ref="52"  />
            <ColorMapEntry rgb="8,118,157" transparent="false" sourceValue="[7.58,7.77)" value="[7.58,7.77)" label="7.58 - 7.77 °C" ref="53"  />
            <ColorMapEntry rgb="8,123,158" transparent="false" sourceValue="[7.77,7.95)" value="[7.77,7.95)" label="7.77 - 7.95 °C" ref="54"  />
            <ColorMapEntry rgb="8,128,159" transparent="false" sourceValue="[7.95,8.14)" value="[7.95,8.14)" label="7.95 - 8.14 °C" ref="55"  />
            <ColorMapEntry rgb="8,133,159" transparent="false" sourceValue="[8.14,8.32)" value="[8.14,8.32)" label="8.14 - 8.32 °C" ref="56"  />
            <ColorMapEntry rgb="8,136,160" transparent="false" sourceValue="[8.32,8.51)" value="[8.32,8.51)" label="8.32 - 8.51 °C" ref="57"  />
            <ColorMapEntry rgb="8,140,162" transparent="false" sourceValue="[8.51,8.69)" value="[8.51,8.69)" label="8.51 - 8.69 °C" ref="58"  />
            <ColorMapEntry rgb="8,145,163" transparent="false" sourceValue="[8.69,8.87)" value="[8.69,8.87)" label="8.69 - 8.87 °C" ref="59"  />
            <ColorMapEntry rgb="8,150,165" transparent="false" sourceValue="[8.87,9.06)" value="[8.87,9.06)" label="8.87 - 9.06 °C" ref="60"  />
            <ColorMapEntry rgb="8,156,166" transparent="false" sourceValue="[9.06,9.24)" value="[9.06,9.24)" label="9.06 - 9.24 °C" ref="61"  />
            <ColorMapEntry rgb="8,161,167" transparent="false" sourceValue="[9.24,9.43)" value="[9.24,9.43)" label="9.24 - 9.43 °C" ref="62"  />
            <ColorMapEntry rgb="8,166,169" transparent="false" sourceValue="[9.43,9.61)" value="[9.43,9.61)" label="9.43 - 9.61 °C" ref="63"  />
            <ColorMapEntry rgb="8,172,172" transparent="false" sourceValue="[9.61,9.8)" value="[9.61,9.8)" label="9.61 - 9.8 °C" ref="64"  />
            <ColorMapEntry rgb="8,177,177" transparent="false" sourceValue="[9.8,9.98)" value="[9.8,9.98)" label="9.8 - 9.98 °C" ref="65"  />
            <ColorMapEntry rgb="8,182,182" transparent="false" sourceValue="[9.98,10.16)" value="[9.98,10.16)" label="9.98 - 10.16 °C" ref="66"  />
            <ColorMapEntry rgb="8,187,187" transparent="false" sourceValue="[10.16,10.35)" value="[10.16,10.35)" label="10.16 - 10.35 °C" ref="67"  />
            <ColorMapEntry rgb="8,192,192" transparent="false" sourceValue="[10.35,10.53)" value="[10.35,10.53)" label="10.35 - 10.53 °C" ref="68"  />
            <ColorMapEntry rgb="8,197,197" transparent="false" sourceValue="[10.53,10.72)" value="[10.53,10.72)" label="10.53 - 10.72 °C" ref="69"  />
            <ColorMapEntry rgb="8,200,200" transparent="false" sourceValue="[10.72,10.9)" value="[10.72,10.9)" label="10.72 - 10.9 °C" ref="70"  />
            <ColorMapEntry rgb="8,204,204" transparent="false" sourceValue="[10.9,11.09)" value="[10.9,11.09)" label="10.9 - 11.09 °C" ref="71"  />
            <ColorMapEntry rgb="8,209,209" transparent="false" sourceValue="[11.09,11.27)" value="[11.09,11.27)" label="11.09 - 11.27 °C" ref="72"  />
            <ColorMapEntry rgb="8,213,213" transparent="false" sourceValue="[11.27,11.45)" value="[11.27,11.45)" label="11.27 - 11.45 °C" ref="73"  />
            <ColorMapEntry rgb="8,216,216" transparent="false" sourceValue="[11.45,11.64)" value="[11.45,11.64)" label="11.45 - 11.64 °C" ref="74"  />
            <ColorMapEntry rgb="8,219,219" transparent="false" sourceValue="[11.64,11.82)" value="[11.64,11.82)" label="11.64 - 11.82 °C" ref="75"  />
            <ColorMapEntry rgb="8,222,222" transparent="false" sourceValue="[11.82,12.01)" value="[11.82,12.01)" label="11.82 - 12.01 °C" ref="76"  />
            <ColorMapEntry rgb="8,225,225" transparent="false" sourceValue="[12.01,12.19)" value="[12.01,12.19)" label="12.01 - 12.19 °C" ref="77"  />
            <ColorMapEntry rgb="8,227,227" transparent="false" sourceValue="[12.19,12.38)" value="[12.19,12.38)" label="12.19 - 12.38 °C" ref="78"  />
            <ColorMapEntry rgb="8,230,230" transparent="false" sourceValue="[12.38,12.56)" value="[12.38,12.56)" label="12.38 - 12.56 °C" ref="79"  />
            <ColorMapEntry rgb="8,233,233" transparent="false" sourceValue="[12.56,12.75)" value="[12.56,12.75)" label="12.56 - 12.75 °C" ref="80"  />
            <ColorMapEntry rgb="8,235,235" transparent="false" sourceValue="[12.75,12.93)" value="[12.75,12.93)" label="12.75 - 12.93 °C" ref="81"  />
            <ColorMapEntry rgb="8,237,236" transparent="false" sourceValue="[12.93,13.11)" value="[12.93,13.11)" label="12.93 - 13.11 °C" ref="82"  />
            <ColorMapEntry rgb="8,238,234" transparent="false" sourceValue="[13.11,13.3)" value="[13.11,13.3)" label="13.11 - 13.3 °C" ref="83"  />
            <ColorMapEntry rgb="8,238,229" transparent="false" sourceValue="[13.3,13.48)" value="[13.3,13.48)" label="13.3 - 13.48 °C" ref="84"  />
            <ColorMapEntry rgb="8,238,223" transparent="false" sourceValue="[13.48,13.67)" value="[13.48,13.67)" label="13.48 - 13.67 °C" ref="85"  />
            <ColorMapEntry rgb="8,237,216" transparent="false" sourceValue="[13.67,13.85)" value="[13.67,13.85)" label="13.67 - 13.85 °C" ref="86"  />
            <ColorMapEntry rgb="8,235,209" transparent="false" sourceValue="[13.85,14.04)" value="[13.85,14.04)" label="13.85 - 14.04 °C" ref="87"  />
            <ColorMapEntry rgb="8,234,202" transparent="false" sourceValue="[14.04,14.22)" value="[14.04,14.22)" label="14.04 - 14.22 °C" ref="88"  />
            <ColorMapEntry rgb="8,232,192" transparent="false" sourceValue="[14.22,14.4)" value="[14.22,14.4)" label="14.22 - 14.4 °C" ref="89"  />
            <ColorMapEntry rgb="8,231,178" transparent="false" sourceValue="[14.4,14.59)" value="[14.4,14.59)" label="14.4 - 14.59 °C" ref="90"  />
            <ColorMapEntry rgb="8,230,162" transparent="false" sourceValue="[14.59,14.77)" value="[14.59,14.77)" label="14.59 - 14.77 °C" ref="91"  />
            <ColorMapEntry rgb="8,229,147" transparent="false" sourceValue="[14.77,14.96)" value="[14.77,14.96)" label="14.77 - 14.96 °C" ref="92"  />
            <ColorMapEntry rgb="8,227,133" transparent="false" sourceValue="[14.96,15.14)" value="[14.96,15.14)" label="14.96 - 15.14 °C" ref="93"  />
            <ColorMapEntry rgb="8,226,123" transparent="false" sourceValue="[15.14,15.33)" value="[15.14,15.33)" label="15.14 - 15.33 °C" ref="94"  />
            <ColorMapEntry rgb="8,224,116" transparent="false" sourceValue="[15.33,15.51)" value="[15.33,15.51)" label="15.33 - 15.51 °C" ref="95"  />
            <ColorMapEntry rgb="8,221,114" transparent="false" sourceValue="[15.51,15.69)" value="[15.51,15.69)" label="15.51 - 15.69 °C" ref="96"  />
            <ColorMapEntry rgb="8,219,114" transparent="false" sourceValue="[15.69,15.88)" value="[15.69,15.88)" label="15.69 - 15.88 °C" ref="97"  />
            <ColorMapEntry rgb="8,216,115" transparent="false" sourceValue="[15.88,16.06)" value="[15.88,16.06)" label="15.88 - 16.06 °C" ref="98"  />
            <ColorMapEntry rgb="8,213,117" transparent="false" sourceValue="[16.06,16.25)" value="[16.06,16.25)" label="16.06 - 16.25 °C" ref="99"  />
            <ColorMapEntry rgb="8,209,118" transparent="false" sourceValue="[16.25,16.43)" value="[16.25,16.43)" label="16.25 - 16.43 °C" ref="100"  />
            <ColorMapEntry rgb="8,204,118" transparent="false" sourceValue="[16.43,16.62)" value="[16.43,16.62)" label="16.43 - 16.62 °C" ref="101"  />
            <ColorMapEntry rgb="8,199,117" transparent="false" sourceValue="[16.62,16.8)" value="[16.62,16.8)" label="16.62 - 16.8 °C" ref="102"  />
            <ColorMapEntry rgb="8,193,115" transparent="false" sourceValue="[16.8,16.98)" value="[16.8,16.98)" label="16.8 - 16.98 °C" ref="103"  />
            <ColorMapEntry rgb="8,188,112" transparent="false" sourceValue="[16.98,17.17)" value="[16.98,17.17)" label="16.98 - 17.17 °C" ref="104"  />
            <ColorMapEntry rgb="8,184,107" transparent="false" sourceValue="[17.17,17.35)" value="[17.17,17.35)" label="17.17 - 17.35 °C" ref="105"  />
            <ColorMapEntry rgb="8,181,99" transparent="false" sourceValue="[17.35,17.54)" value="[17.35,17.54)" label="17.35 - 17.54 °C" ref="106"  />
            <ColorMapEntry rgb="8,178,91" transparent="false" sourceValue="[17.54,17.72)" value="[17.54,17.72)" label="17.54 - 17.72 °C" ref="107"  />
            <ColorMapEntry rgb="8,175,84" transparent="false" sourceValue="[17.72,17.91)" value="[17.72,17.91)" label="17.72 - 17.91 °C" ref="108"  />
            <ColorMapEntry rgb="8,172,81" transparent="false" sourceValue="[17.91,18.09)" value="[17.91,18.09)" label="17.91 - 18.09 °C" ref="109"  />
            <ColorMapEntry rgb="8,169,80" transparent="false" sourceValue="[18.09,18.27)" value="[18.09,18.27)" label="18.09 - 18.27 °C" ref="110"  />
            <ColorMapEntry rgb="8,164,80" transparent="false" sourceValue="[18.27,18.46)" value="[18.27,18.46)" label="18.27 - 18.46 °C" ref="111"  />
            <ColorMapEntry rgb="8,159,80" transparent="false" sourceValue="[18.46,18.64)" value="[18.46,18.64)" label="18.46 - 18.64 °C" ref="112"  />
            <ColorMapEntry rgb="8,153,80" transparent="false" sourceValue="[18.64,18.83)" value="[18.64,18.83)" label="18.64 - 18.83 °C" ref="113"  />
            <ColorMapEntry rgb="8,148,79" transparent="false" sourceValue="[18.83,19.01)" value="[18.83,19.01)" label="18.83 - 19.01 °C" ref="114"  />
            <ColorMapEntry rgb="8,143,79" transparent="false" sourceValue="[19.01,19.2)" value="[19.01,19.2)" label="19.01 - 19.2 °C" ref="115"  />
            <ColorMapEntry rgb="8,138,79" transparent="false" sourceValue="[19.2,19.38)" value="[19.2,19.38)" label="19.2 - 19.38 °C" ref="116"  />
            <ColorMapEntry rgb="8,134,78" transparent="false" sourceValue="[19.38,19.56)" value="[19.38,19.56)" label="19.38 - 19.56 °C" ref="117"  />
            <ColorMapEntry rgb="8,132,75" transparent="false" sourceValue="[19.56,19.75)" value="[19.56,19.75)" label="19.56 - 19.75 °C" ref="118"  />
            <ColorMapEntry rgb="8,134,70" transparent="false" sourceValue="[19.75,19.93)" value="[19.75,19.93)" label="19.75 - 19.93 °C" ref="119"  />
            <ColorMapEntry rgb="8,137,63" transparent="false" sourceValue="[19.93,20.12)" value="[19.93,20.12)" label="19.93 - 20.12 °C" ref="120"  />
            <ColorMapEntry rgb="8,140,56" transparent="false" sourceValue="[20.12,20.3)" value="[20.12,20.3)" label="20.12 - 20.3 °C" ref="121"  />
            <ColorMapEntry rgb="8,140,48" transparent="false" sourceValue="[20.3,20.49)" value="[20.3,20.49)" label="20.3 - 20.49 °C" ref="122"  />
            <ColorMapEntry rgb="8,139,37" transparent="false" sourceValue="[20.49,20.67)" value="[20.49,20.67)" label="20.49 - 20.67 °C" ref="123"  />
            <ColorMapEntry rgb="9,138,24" transparent="false" sourceValue="[20.67,20.85)" value="[20.67,20.85)" label="20.67 - 20.85 °C" ref="124"  />
            <ColorMapEntry rgb="14,139,14" transparent="false" sourceValue="[20.85,21.04)" value="[20.85,21.04)" label="20.85 - 21.04 °C" ref="125"  />
            <ColorMapEntry rgb="24,141,9" transparent="false" sourceValue="[21.04,21.22)" value="[21.04,21.22)" label="21.04 - 21.22 °C" ref="126"  />
            <ColorMapEntry rgb="37,146,8" transparent="false" sourceValue="[21.22,21.41)" value="[21.22,21.41)" label="21.22 - 21.41 °C" ref="127"  />
            <ColorMapEntry rgb="47,151,8" transparent="false" sourceValue="[21.41,21.59)" value="[21.41,21.59)" label="21.41 - 21.59 °C" ref="128"  />
            <ColorMapEntry rgb="52,156,8" transparent="false" sourceValue="[21.59,21.78)" value="[21.59,21.78)" label="21.59 - 21.78 °C" ref="129"  />
            <ColorMapEntry rgb="55,161,8" transparent="false" sourceValue="[21.78,21.96)" value="[21.78,21.96)" label="21.78 - 21.96 °C" ref="130"  />
            <ColorMapEntry rgb="57,166,8" transparent="false" sourceValue="[21.96,22.15)" value="[21.96,22.15)" label="21.96 - 22.15 °C" ref="131"  />
            <ColorMapEntry rgb="60,172,8" transparent="false" sourceValue="[22.15,22.33)" value="[22.15,22.33)" label="22.15 - 22.33 °C" ref="132"  />
            <ColorMapEntry rgb="65,177,8" transparent="false" sourceValue="[22.33,22.51)" value="[22.33,22.51)" label="22.33 - 22.51 °C" ref="133"  />
            <ColorMapEntry rgb="70,182,8" transparent="false" sourceValue="[22.51,22.7)" value="[22.51,22.7)" label="22.51 - 22.7 °C" ref="134"  />
            <ColorMapEntry rgb="75,187,8" transparent="false" sourceValue="[22.7,22.88)" value="[22.7,22.88)" label="22.7 - 22.88 °C" ref="135"  />
            <ColorMapEntry rgb="80,192,8" transparent="false" sourceValue="[22.88,23.07)" value="[22.88,23.07)" label="22.88 - 23.07 °C" ref="136"  />
            <ColorMapEntry rgb="85,196,8" transparent="false" sourceValue="[23.07,23.25)" value="[23.07,23.25)" label="23.07 - 23.25 °C" ref="137"  />
            <ColorMapEntry rgb="89,199,8" transparent="false" sourceValue="[23.25,23.44)" value="[23.25,23.44)" label="23.25 - 23.44 °C" ref="138"  />
            <ColorMapEntry rgb="95,201,8" transparent="false" sourceValue="[23.44,23.62)" value="[23.44,23.62)" label="23.44 - 23.62 °C" ref="139"  />
            <ColorMapEntry rgb="103,204,8" transparent="false" sourceValue="[23.62,23.8)" value="[23.62,23.8)" label="23.62 - 23.8 °C" ref="140"  />
            <ColorMapEntry rgb="110,206,8" transparent="false" sourceValue="[23.8,23.99)" value="[23.8,23.99)" label="23.8 - 23.99 °C" ref="141"  />
            <ColorMapEntry rgb="118,209,8" transparent="false" sourceValue="[23.99,24.17)" value="[23.99,24.17)" label="23.99 - 24.17 °C" ref="142"  />
            <ColorMapEntry rgb="126,211,8" transparent="false" sourceValue="[24.17,24.36)" value="[24.17,24.36)" label="24.17 - 24.36 °C" ref="143"  />
            <ColorMapEntry rgb="134,214,8" transparent="false" sourceValue="[24.36,24.54)" value="[24.36,24.54)" label="24.36 - 24.54 °C" ref="144"  />
            <ColorMapEntry rgb="142,217,8" transparent="false" sourceValue="[24.54,24.73)" value="[24.54,24.73)" label="24.54 - 24.73 °C" ref="145"  />
            <ColorMapEntry rgb="151,219,8" transparent="false" sourceValue="[24.73,24.91)" value="[24.73,24.91)" label="24.73 - 24.91 °C" ref="146"  />
            <ColorMapEntry rgb="160,222,8" transparent="false" sourceValue="[24.91,25.09)" value="[24.91,25.09)" label="24.91 - 25.09 °C" ref="147"  />
            <ColorMapEntry rgb="169,225,8" transparent="false" sourceValue="[25.09,25.28)" value="[25.09,25.28)" label="25.09 - 25.28 °C" ref="148"  />
            <ColorMapEntry rgb="179,227,8" transparent="false" sourceValue="[25.28,25.46)" value="[25.28,25.46)" label="25.28 - 25.46 °C" ref="149"  />
            <ColorMapEntry rgb="187,229,8" transparent="false" sourceValue="[25.46,25.65)" value="[25.46,25.65)" label="25.46 - 25.65 °C" ref="150"  />
            <ColorMapEntry rgb="195,230,8" transparent="false" sourceValue="[25.65,25.83)" value="[25.65,25.83)" label="25.65 - 25.83 °C" ref="151"  />
            <ColorMapEntry rgb="205,230,8" transparent="false" sourceValue="[25.83,26.02)" value="[25.83,26.02)" label="25.83 - 26.02 °C" ref="152"  />
            <ColorMapEntry rgb="215,230,8" transparent="false" sourceValue="[26.02,26.2)" value="[26.02,26.2)" label="26.02 - 26.2 °C" ref="153"  />
            <ColorMapEntry rgb="223,229,8" transparent="false" sourceValue="[26.2,26.38)" value="[26.2,26.38)" label="26.2 - 26.38 °C" ref="154"  />
            <ColorMapEntry rgb="226,227,8" transparent="false" sourceValue="[26.38,26.57)" value="[26.38,26.57)" label="26.38 - 26.57 °C" ref="155"  />
            <ColorMapEntry rgb="225,224,8" transparent="false" sourceValue="[26.57,26.75)" value="[26.57,26.75)" label="26.57 - 26.75 °C" ref="156"  />
            <ColorMapEntry rgb="224,221,8" transparent="false" sourceValue="[26.75,26.94)" value="[26.75,26.94)" label="26.75 - 26.94 °C" ref="157"  />
            <ColorMapEntry rgb="224,217,8" transparent="false" sourceValue="[26.94,27.12)" value="[26.94,27.12)" label="26.94 - 27.12 °C" ref="158"  />
            <ColorMapEntry rgb="224,211,8" transparent="false" sourceValue="[27.12,27.31)" value="[27.12,27.31)" label="27.12 - 27.31 °C" ref="159"  />
            <ColorMapEntry rgb="224,205,8" transparent="false" sourceValue="[27.31,27.49)" value="[27.31,27.49)" label="27.31 - 27.49 °C" ref="160"  />
            <ColorMapEntry rgb="224,198,8" transparent="false" sourceValue="[27.49,27.67)" value="[27.49,27.67)" label="27.49 - 27.67 °C" ref="161"  />
            <ColorMapEntry rgb="224,191,8" transparent="false" sourceValue="[27.67,27.86)" value="[27.67,27.86)" label="27.67 - 27.86 °C" ref="162"  />
            <ColorMapEntry rgb="224,185,8" transparent="false" sourceValue="[27.86,28.04)" value="[27.86,28.04)" label="27.86 - 28.04 °C" ref="163"  />
            <ColorMapEntry rgb="224,180,8" transparent="false" sourceValue="[28.04,28.23)" value="[28.04,28.23)" label="28.04 - 28.23 °C" ref="164"  />
            <ColorMapEntry rgb="224,174,8" transparent="false" sourceValue="[28.23,28.41)" value="[28.23,28.41)" label="28.23 - 28.41 °C" ref="165"  />
            <ColorMapEntry rgb="224,166,8" transparent="false" sourceValue="[28.41,28.6)" value="[28.41,28.6)" label="28.41 - 28.6 °C" ref="166"  />
            <ColorMapEntry rgb="224,159,8" transparent="false" sourceValue="[28.6,28.78)" value="[28.6,28.78)" label="28.6 - 28.78 °C" ref="167"  />
            <ColorMapEntry rgb="224,151,8" transparent="false" sourceValue="[28.78,28.96)" value="[28.78,28.96)" label="28.78 - 28.96 °C" ref="168"  />
            <ColorMapEntry rgb="224,143,8" transparent="false" sourceValue="[28.96,29.15)" value="[28.96,29.15)" label="28.96 - 29.15 °C" ref="169"  />
            <ColorMapEntry rgb="224,135,8" transparent="false" sourceValue="[29.15,29.33)" value="[29.15,29.33)" label="29.15 - 29.33 °C" ref="170"  />
            <ColorMapEntry rgb="224,127,8" transparent="false" sourceValue="[29.33,29.52)" value="[29.33,29.52)" label="29.33 - 29.52 °C" ref="171"  />
            <ColorMapEntry rgb="224,119,8" transparent="false" sourceValue="[29.52,29.7)" value="[29.52,29.7)" label="29.52 - 29.7 °C" ref="172"  />
            <ColorMapEntry rgb="224,111,8" transparent="false" sourceValue="[29.7,29.89)" value="[29.7,29.89)" label="29.7 - 29.89 °C" ref="173"  />
            <ColorMapEntry rgb="224,103,8" transparent="false" sourceValue="[29.89,30.07)" value="[29.89,30.07)" label="29.89 - 30.07 °C" ref="174"  />
            <ColorMapEntry rgb="224,95,8" transparent="false" sourceValue="[30.07,30.25)" value="[30.07,30.25)" label="30.07 - 30.25 °C" ref="175"  />
            <ColorMapEntry rgb="224,89,8" transparent="false" sourceValue="[30.25,30.44)" value="[30.25,30.44)" label="30.25 - 30.44 °C" ref="176"  />
            <ColorMapEntry rgb="224,84,8" transparent="false" sourceValue="[30.44,30.62)" value="[30.44,30.62)" label="30.44 - 30.62 °C" ref="177"  />
            <ColorMapEntry rgb="224,78,8" transparent="false" sourceValue="[30.62,30.81)" value="[30.62,30.81)" label="30.62 - 30.81 °C" ref="178"  />
            <ColorMapEntry rgb="223,70,8" transparent="false" sourceValue="[30.81,30.99)" value="[30.81,30.99)" label="30.81 - 30.99 °C" ref="179"  />
            <ColorMapEntry rgb="223,63,8" transparent="false" sourceValue="[30.99,31.18)" value="[30.99,31.18)" label="30.99 - 31.18 °C" ref="180"  />
            <ColorMapEntry rgb="223,55,8" transparent="false" sourceValue="[31.18,31.36)" value="[31.18,31.36)" label="31.18 - 31.36 °C" ref="181"  />
            <ColorMapEntry rgb="222,46,8" transparent="false" sourceValue="[31.36,31.55)" value="[31.36,31.55)" label="31.36 - 31.55 °C" ref="182"  />
            <ColorMapEntry rgb="221,37,8" transparent="false" sourceValue="[31.55,31.73)" value="[31.55,31.73)" label="31.55 - 31.73 °C" ref="183"  />
            <ColorMapEntry rgb="219,28,8" transparent="false" sourceValue="[31.73,31.91)" value="[31.73,31.91)" label="31.73 - 31.91 °C" ref="184"  />
            <ColorMapEntry rgb="216,19,8" transparent="false" sourceValue="[31.91,32.1)" value="[31.91,32.1)" label="31.91 - 32.1 °C" ref="185"  />
            <ColorMapEntry rgb="213,12,8" transparent="false" sourceValue="[32.1,32.28)" value="[32.1,32.28)" label="32.1 - 32.28 °C" ref="186"  />
            <ColorMapEntry rgb="209,9,8" transparent="false" sourceValue="[32.28,32.47)" value="[32.28,32.47)" label="32.28 - 32.47 °C" ref="187"  />
            <ColorMapEntry rgb="204,8,8" transparent="false" sourceValue="[32.47,32.65)" value="[32.47,32.65)" label="32.47 - 32.65 °C" ref="188"  />
            <ColorMapEntry rgb="200,8,8" transparent="false" sourceValue="[32.65,32.84)" value="[32.65,32.84)" label="32.65 - 32.84 °C" ref="189"  />
            <ColorMapEntry rgb="196,8,8" transparent="false" sourceValue="[32.84,33.02)" value="[32.84,33.02)" label="32.84 - 33.02 °C" ref="190"  />
            <ColorMapEntry rgb="190,8,8" transparent="false" sourceValue="[33.02,33.2)" value="[33.02,33.2)" label="33.02 - 33.2 °C" ref="191"  />
            <ColorMapEntry rgb="182,8,8" transparent="false" sourceValue="[33.2,33.39)" value="[33.2,33.39)" label="33.2 - 33.39 °C" ref="192"  />
            <ColorMapEntry rgb="175,8,8" transparent="false" sourceValue="[33.39,33.57)" value="[33.39,33.57)" label="33.39 - 33.57 °C" ref="193"  />
            <ColorMapEntry rgb="167,8,8" transparent="false" sourceValue="[33.57,33.76)" value="[33.57,33.76)" label="33.57 - 33.76 °C" ref="194"  />
            <ColorMapEntry rgb="159,8,8" transparent="false" sourceValue="[33.76,33.94)" value="[33.76,33.94)" label="33.76 - 33.94 °C" ref="195"  />
            <ColorMapEntry rgb="151,8,8" transparent="false" sourceValue="[33.94,34.13)" value="[33.94,34.13)" label="33.94 - 34.13 °C" ref="196"  />
            <ColorMapEntry rgb="143,8,8" transparent="false" sourceValue="[34.13,34.31)" value="[34.13,34.31)" label="34.13 - 34.31 °C" ref="197"  />
            <ColorMapEntry rgb="135,8,8" transparent="false" sourceValue="[34.31,34.49)" value="[34.31,34.49)" label="34.31 - 34.49 °C" ref="198"  />
            <ColorMapEntry rgb="127,8,8" transparent="false" sourceValue="[34.49,34.68)" value="[34.49,34.68)" label="34.49 - 34.68 °C" ref="199"  />
            <ColorMapEntry rgb="120,8,8" transparent="false" sourceValue="[34.68,34.86)" value="[34.68,34.86)" label="34.68 - 34.86 °C" ref="200"  />
            <ColorMapEntry rgb="115,8,8" transparent="false" sourceValue="[34.86,35.05)" value="[34.86,35.05)" label="34.86 - 35.05 °C" ref="201"  />
            <ColorMapEntry rgb="110,8,8" transparent="false" sourceValue="[35.05,35.23)" value="[35.05,35.23)" label="35.05 - 35.23 °C" ref="202"  />
            <ColorMapEntry rgb="104,8,8" transparent="false" sourceValue="[35.23,35.42)" value="[35.23,35.42)" label="35.23 - 35.42 °C" ref="203"  />
            <ColorMapEntry rgb="108,13,13" transparent="false" sourceValue="[35.42,35.6)" value="[35.42,35.6)" label="35.42 - 35.6 °C" ref="204"  />
            <ColorMapEntry rgb="112,19,19" transparent="false" sourceValue="[35.6,35.78)" value="[35.6,35.78)" label="35.6 - 35.78 °C" ref="205"  />
            <ColorMapEntry rgb="114,22,22" transparent="false" sourceValue="[35.78,35.97)" value="[35.78,35.97)" label="35.78 - 35.97 °C" ref="206"  />
            <ColorMapEntry rgb="115,26,26" transparent="false" sourceValue="[35.97,36.15)" value="[35.97,36.15)" label="35.97 - 36.15 °C" ref="207"  />
            <ColorMapEntry rgb="118,30,30" transparent="false" sourceValue="[36.15,36.34)" value="[36.15,36.34)" label="36.15 - 36.34 °C" ref="208"  />
            <ColorMapEntry rgb="119,34,33" transparent="false" sourceValue="[36.34,36.52)" value="[36.34,36.52)" label="36.34 - 36.52 °C" ref="209"  />
            <ColorMapEntry rgb="121,38,38" transparent="false" sourceValue="[36.52,36.71)" value="[36.52,36.71)" label="36.52 - 36.71 °C" ref="210"  />
            <ColorMapEntry rgb="123,41,41" transparent="false" sourceValue="[36.71,36.89)" value="[36.71,36.89)" label="36.71 - 36.89 °C" ref="211"  />
            <ColorMapEntry rgb="125,45,45" transparent="false" sourceValue="[36.89,37.07)" value="[36.89,37.07)" label="36.89 - 37.07 °C" ref="212"  />
            <ColorMapEntry rgb="127,49,49" transparent="false" sourceValue="[37.07,37.26)" value="[37.07,37.26)" label="37.07 - 37.26 °C" ref="213"  />
            <ColorMapEntry rgb="128,52,53" transparent="false" sourceValue="[37.26,37.44)" value="[37.26,37.44)" label="37.26 - 37.44 °C" ref="214"  />
            <ColorMapEntry rgb="130,56,56" transparent="false" sourceValue="[37.44,37.63)" value="[37.44,37.63)" label="37.44 - 37.63 °C" ref="215"  />
            <ColorMapEntry rgb="132,60,60" transparent="false" sourceValue="[37.63,37.81)" value="[37.63,37.81)" label="37.63 - 37.81 °C" ref="216"  />
            <ColorMapEntry rgb="134,64,63" transparent="false" sourceValue="[37.81,38)" value="[37.81,38)" label="37.81 - 38 °C" ref="217"  />
            <ColorMapEntry rgb="136,67,67" transparent="false" sourceValue="[38,38.18)" value="[38,38.18)" label="38 - 38.18 °C" ref="218"  />
            <ColorMapEntry rgb="138,71,70" transparent="false" sourceValue="[38.18,38.36)" value="[38.18,38.36)" label="38.18 - 38.36 °C" ref="219"  />
            <ColorMapEntry rgb="140,75,74" transparent="false" sourceValue="[38.36,38.55)" value="[38.36,38.55)" label="38.36 - 38.55 °C" ref="220"  />
            <ColorMapEntry rgb="142,79,78" transparent="false" sourceValue="[38.55,38.73)" value="[38.55,38.73)" label="38.55 - 38.73 °C" ref="221"  />
            <ColorMapEntry rgb="143,82,82" transparent="false" sourceValue="[38.73,38.92)" value="[38.73,38.92)" label="38.73 - 38.92 °C" ref="222"  />
            <ColorMapEntry rgb="145,85,85" transparent="false" sourceValue="[38.92,39.1)" value="[38.92,39.1)" label="38.92 - 39.1 °C" ref="223"  />
            <ColorMapEntry rgb="147,89,90" transparent="false" sourceValue="[39.1,39.29)" value="[39.1,39.29)" label="39.1 - 39.29 °C" ref="224"  />
            <ColorMapEntry rgb="149,93,93" transparent="false" sourceValue="[39.29,39.47)" value="[39.29,39.47)" label="39.29 - 39.47 °C" ref="225"  />
            <ColorMapEntry rgb="150,97,97" transparent="false" sourceValue="[39.47,39.65)" value="[39.47,39.65)" label="39.47 - 39.65 °C" ref="226"  />
            <ColorMapEntry rgb="152,100,100" transparent="false" sourceValue="[39.65,39.84)" value="[39.65,39.84)" label="39.65 - 39.84 °C" ref="227"  />
            <ColorMapEntry rgb="154,104,104" transparent="false" sourceValue="[39.84,40.02)" value="[39.84,40.02)" label="39.84 - 40.02 °C" ref="228"  />
            <ColorMapEntry rgb="156,107,108" transparent="false" sourceValue="[40.02,40.21)" value="[40.02,40.21)" label="40.02 - 40.21 °C" ref="229"  />
            <ColorMapEntry rgb="158,112,111" transparent="false" sourceValue="[40.21,40.39)" value="[40.21,40.39)" label="40.21 - 40.39 °C" ref="230"  />
            <ColorMapEntry rgb="160,115,115" transparent="false" sourceValue="[40.39,40.58)" value="[40.39,40.58)" label="40.39 - 40.58 °C" ref="231"  />
            <ColorMapEntry rgb="162,119,119" transparent="false" sourceValue="[40.58,40.76)" value="[40.58,40.76)" label="40.58 - 40.76 °C" ref="232"  />
            <ColorMapEntry rgb="164,123,123" transparent="false" sourceValue="[40.76,40.95)" value="[40.76,40.95)" label="40.76 - 40.95 °C" ref="233"  />
            <ColorMapEntry rgb="165,126,126" transparent="false" sourceValue="[40.95,41.13)" value="[40.95,41.13)" label="40.95 - 41.13 °C" ref="234"  />
            <ColorMapEntry rgb="168,130,130" transparent="false" sourceValue="[41.13,41.31)" value="[41.13,41.31)" label="41.13 - 41.31 °C" ref="235"  />
            <ColorMapEntry rgb="169,134,134" transparent="false" sourceValue="[41.31,41.5)" value="[41.31,41.5)" label="41.31 - 41.5 °C" ref="236"  />
            <ColorMapEntry rgb="170,138,137" transparent="false" sourceValue="[41.5,41.68)" value="[41.5,41.68)" label="41.5 - 41.68 °C" ref="237"  />
            <ColorMapEntry rgb="173,141,141" transparent="false" sourceValue="[41.68,41.87)" value="[41.68,41.87)" label="41.68 - 41.87 °C" ref="238"  />
            <ColorMapEntry rgb="175,145,145" transparent="false" sourceValue="[41.87,42.05)" value="[41.87,42.05)" label="41.87 - 42.05 °C" ref="239"  />
            <ColorMapEntry rgb="176,149,149" transparent="false" sourceValue="[42.05,42.24)" value="[42.05,42.24)" label="42.05 - 42.24 °C" ref="240"  />
            <ColorMapEntry rgb="178,153,153" transparent="false" sourceValue="[42.24,42.42)" value="[42.24,42.42)" label="42.24 - 42.42 °C" ref="241"  />
            <ColorMapEntry rgb="181,156,156" transparent="false" sourceValue="[42.42,42.6)" value="[42.42,42.6)" label="42.42 - 42.6 °C" ref="242"  />
            <ColorMapEntry rgb="182,159,159" transparent="false" sourceValue="[42.6,42.79)" value="[42.6,42.79)" label="42.6 - 42.79 °C" ref="243"  />
            <ColorMapEntry rgb="183,163,163" transparent="false" sourceValue="[42.79,42.97)" value="[42.79,42.97)" label="42.79 - 42.97 °C" ref="244"  />
            <ColorMapEntry rgb="185,167,167" transparent="false" sourceValue="[42.97,43.16)" value="[42.97,43.16)" label="42.97 - 43.16 °C" ref="245"  />
            <ColorMapEntry rgb="188,170,171" transparent="false" sourceValue="[43.16,43.34)" value="[43.16,43.34)" label="43.16 - 43.34 °C" ref="246"  />
            <ColorMapEntry rgb="190,174,174" transparent="false" sourceValue="[43.34,43.53)" value="[43.34,43.53)" label="43.34 - 43.53 °C" ref="247"  />
            <ColorMapEntry rgb="191,178,178" transparent="false" sourceValue="[43.53,43.71)" value="[43.53,43.71)" label="43.53 - 43.71 °C" ref="248"  />
            <ColorMapEntry rgb="193,182,182" transparent="false" sourceValue="[43.71,43.89)" value="[43.71,43.89)" label="43.71 - 43.89 °C" ref="249"  />
            <ColorMapEntry rgb="195,185,185" transparent="false" sourceValue="[43.89,44.08)" value="[43.89,44.08)" label="43.89 - 44.08 °C" ref="250"  />
            <ColorMapEntry rgb="197,189,189" transparent="false" sourceValue="[44.08,44.26)" value="[44.08,44.26)" label="44.08 - 44.26 °C" ref="251"  />
            <ColorMapEntry rgb="199,192,193" transparent="false" sourceValue="[44.26,44.45)" value="[44.26,44.45)" label="44.26 - 44.45 °C" ref="252"  />
            <ColorMapEntry rgb="200,197,197" transparent="false" sourceValue="[44.45,44.63)" value="[44.45,44.63)" label="44.45 - 44.63 °C" ref="253"  />
            <ColorMapEntry rgb="202,200,201" transparent="false" sourceValue="[44.63,44.82)" value="[44.63,44.82)" label="44.63 - 44.82 °C" ref="254"  />
            <ColorMapEntry rgb="204,204,204" transparent="false" sourceValue="[44.82,45]" value="[44.82,45]" label="44.82 - 45 °C" ref="255"  />
        </Entries>
        <Legend type="continuous" minLabel="-2 °C" maxLabel="45 °C">
            <LegendEntry rgb="91,10,118"  id="1"  />
            <LegendEntry rgb="99,9,139"  id="2"  />
            <LegendEntry rgb="112,7,171"  id="3"  />
            <LegendEntry rgb="124,7,202"  id="4"  />
            <LegendEntry rgb="130,7,223"  id="5"  />
            <LegendEntry rgb="128,7,234"  id="6"  />
            <LegendEntry rgb="120,7,238"  id="7"  />
            <LegendEntry rgb="110,7,238"  id="8"  />
            <LegendEntry rgb="100,7,239"  id="9"  />
            <LegendEntry rgb="88,7,239"  id="10"  />
            <LegendEntry rgb="73,7,239"  id="11"  />
            <LegendEntry rgb="54,7,239"  id="12"  />
            <LegendEntry rgb="34,8,238"  id="13"  />
            <LegendEntry rgb="18,8,236"  id="14"  />
            <LegendEntry rgb="11,8,233"  id="15"  />
            <LegendEntry rgb="8,8,228"  id="16"  />
            <LegendEntry rgb="8,8,224"  id="17"  />
            <LegendEntry rgb="8,8,221"  id="18"  />
            <LegendEntry rgb="8,8,217"  id="19"  />
            <LegendEntry rgb="8,8,212"  id="20"  />
            <LegendEntry rgb="8,8,207"  id="21"  />
            <LegendEntry rgb="8,8,201"  id="22"  />
            <LegendEntry rgb="8,8,196"  id="23"  />
            <LegendEntry rgb="8,8,191"  id="24"  />
            <LegendEntry rgb="8,8,185"  id="25"  />
            <LegendEntry rgb="8,8,179"  id="26"  />
            <LegendEntry rgb="8,8,173"  id="27"  />
            <LegendEntry rgb="8,8,166"  id="28"  />
            <LegendEntry rgb="8,8,159"  id="29"  />
            <LegendEntry rgb="8,8,153"  id="30"  />
            <LegendEntry rgb="8,11,147"  id="31"  />
            <LegendEntry rgb="8,16,139"  id="32"  />
            <LegendEntry rgb="8,23,130"  id="33"  />
            <LegendEntry rgb="8,30,121"  id="34"  />
            <LegendEntry rgb="8,38,114"  id="35"  />
            <LegendEntry rgb="8,46,109"  id="36"  />
            <LegendEntry rgb="8,54,106"  id="37"  />
            <LegendEntry rgb="8,62,104"  id="38"  />
            <LegendEntry rgb="8,70,104"  id="39"  />
            <LegendEntry rgb="8,78,104"  id="40"  />
            <LegendEntry rgb="8,86,106"  id="41"  />
            <LegendEntry rgb="8,93,107"  id="42"  />
            <LegendEntry rgb="8,98,109"  id="43"  />
            <LegendEntry rgb="8,100,112"  id="44"  />
            <LegendEntry rgb="8,99,114"  id="45"  />
            <LegendEntry rgb="8,98,117"  id="46"  />
            <LegendEntry rgb="8,97,122"  id="47"  />
            <LegendEntry rgb="8,98,130"  id="48"  />
            <LegendEntry rgb="8,101,139"  id="49"  />
            <LegendEntry rgb="8,104,147"  id="50"  />
            <LegendEntry rgb="8,108,152"  id="51"  />
            <LegendEntry rgb="8,113,155"  id="52"  />
            <LegendEntry rgb="8,118,157"  id="53"  />
            <LegendEntry rgb="8,123,158"  id="54"  />
            <LegendEntry rgb="8,128,159"  id="55"  />
            <LegendEntry rgb="8,133,159"  id="56"  />
            <LegendEntry rgb="8,136,160"  id="57"  />
            <LegendEntry rgb="8,140,162"  id="58"  />
            <LegendEntry rgb="8,145,163"  id="59"  />
            <LegendEntry rgb="8,150,165"  id="60"  />
            <LegendEntry rgb="8,156,166"  id="61"  />
            <LegendEntry rgb="8,161,167"  id="62"  />
            <LegendEntry rgb="8,166,169"  id="63"  />
            <LegendEntry rgb="8,172,172"  id="64"  />
            <LegendEntry rgb="8,177,177"  id="65"  />
            <LegendEntry rgb="8,182,182"  id="66"  />
            <LegendEntry rgb="8,187,187"  id="67"  />
            <LegendEntry rgb="8,192,192"  id="68"  />
            <LegendEntry rgb="8,197,197"  id="69"  />
            <LegendEntry rgb="8,200,200"  id="70"  />
            <LegendEntry rgb="8,204,204"  id="71"  />
            <LegendEntry rgb="8,209,209"  id="72"  />
            <LegendEntry rgb="8,213,213"  id="73"  />
            <LegendEntry rgb="8,216,216"  id="74"  />
            <LegendEntry rgb="8,219,219"  id="75"  />
            <LegendEntry rgb="8,222,222"  id="76"  />
            <LegendEntry rgb="8,225,225"  id="77"  />
            <LegendEntry rgb="8,227,227"  id="78"  />
            <LegendEntry rgb="8,230,230"  id="79"  />
            <LegendEntry rgb="8,233,233"  id="80"  />
            <LegendEntry rgb="8,235,235"  id="81"  />
            <LegendEntry rgb="8,237,236"  id="82"  />
            <LegendEntry rgb="8,238,234"  id="83"  />
            <LegendEntry rgb="8,238,229"  id="84"  />
            <LegendEntry rgb="8,238,223"  id="85"  />
            <LegendEntry rgb="8,237,216"  id="86"  />
            <LegendEntry rgb="8,235,209"  id="87"  />
            <LegendEntry rgb="8,234,202"  id="88"  />
            <LegendEntry rgb="8,232,192"  id="89"  />
            <LegendEntry rgb="8,231,178"  id="90"  />
            <LegendEntry rgb="8,230,162"  id="91"  />
            <LegendEntry rgb="8,229,147"  id="92"  />
            <LegendEntry rgb="8,227,133"  id="93"  />
            <LegendEntry rgb="8,226,123"  id="94"  />
            <LegendEntry rgb="8,224,116"  id="95"  />
            <LegendEntry rgb="8,221,114"  id="96"  />
            <LegendEntry rgb="8,219,114"  id="97"  />
            <LegendEntry rgb="8,216,115"  id="98"  />
            <LegendEntry rgb="8,213,117"  id="99"  />
            <LegendEntry rgb="8,209,118"  id="100"  />
            <LegendEntry rgb="8,204,118"  id="101"  />
            <LegendEntry rgb="8,199,117"  id="102"  />
            <LegendEntry rgb="8,193,115"  id="103"  />
            <LegendEntry rgb="8,188,112"  id="104"  />
            <LegendEntry rgb="8,184,107"  id="105"  />
            <LegendEntry rgb="8,181,99"  id="106"  />
            <LegendEntry rgb="8,178,91"  id="107"  />
            <LegendEntry rgb="8,175,84"  id="108"  />
            <LegendEntry rgb="8,172,81"  id="109"  />
            <LegendEntry rgb="8,169,80"  id="110"  />
            <LegendEntry rgb="8,164,80"  id="111"  />
            <LegendEntry rgb="8,159,80"  id="112"  />
            <LegendEntry rgb="8,153,80"  id="113"  />
            <LegendEntry rgb="8,148,79"  id="114"  />
            <LegendEntry rgb="8,143,79"  id="115"  />
            <LegendEntry rgb="8,138,79"  id="116"  />
            <LegendEntry rgb="8,134,78"  id="117"  />
            <LegendEntry rgb="8,132,75"  id="118"  />
            <LegendEntry rgb="8,134,70"  id="119"  />
            <LegendEntry rgb="8,137,63"  id="120"  />
            <LegendEntry rgb="8,140,56"  id="121"  />
            <LegendEntry rgb="8,140,48"  id="122"  />
            <LegendEntry rgb="8,139,37"  id="123"  />
            <LegendEntry rgb="9,138,24"  id="124"  />
            <LegendEntry rgb="14,139,14"  id="125"  />
            <LegendEntry rgb="24,141,9"  id="126"  />
            <LegendEntry rgb="37,146,8"  id="127"  />
            <LegendEntry rgb="47,151,8"  id="128"  />
            <LegendEntry rgb="52,156,8"  id="129"  />
            <LegendEntry rgb="55,161,8"  id="130"  />
            <LegendEntry rgb="57,166,8"  id="131"  />
            <LegendEntry rgb="60,172,8"  id="132"  />
            <LegendEntry rgb="65,177,8"  id="133"  />
            <LegendEntry rgb="70,182,8"  id="134"  />
            <LegendEntry rgb="75,187,8"  id="135"  />
            <LegendEntry rgb="80,192,8"  id="136"  />
            <LegendEntry rgb="85,196,8"  id="137"  />
            <LegendEntry rgb="89,199,8"  id="138"  />
            <LegendEntry rgb="95,201,8"  id="139"  />
            <LegendEntry rgb="103,204,8"  id="140"  />
            <LegendEntry rgb="110,206,8"  id="141"  />
            <LegendEntry rgb="118,209,8"  id="142"  />
            <LegendEntry rgb="126,211,8"  id="143"  />
            <LegendEntry rgb="134,214,8"  id="144"  />
            <LegendEntry rgb="142,217,8"  id="145"  />
            <LegendEntry rgb="151,219,8"  id="146"  />
            <LegendEntry rgb="160,222,8"  id="147"  />
            <LegendEntry rgb="169,225,8"  id="148"  />
            <LegendEntry rgb="179,227,8"  id="149"  />
            <LegendEntry rgb="187,229,8"  id="150"  />
            <LegendEntry rgb="195,230,8"  id="151"  />
            <LegendEntry rgb="205,230,8"  id="152"  />
            <LegendEntry rgb="215,230,8"  id="153"  />
            <LegendEntry rgb="223,229,8"  id="154"  />
            <LegendEntry rgb="226,227,8"  id="155"  />
            <LegendEntry rgb="225,224,8"  id="156"  />
            <LegendEntry rgb="224,221,8"  id="157"  />
            <LegendEntry rgb="224,217,8"  id="158"  />
            <LegendEntry rgb="224,211,8"  id="159"  />
            <LegendEntry rgb="224,205,8"  id="160"  />
            <LegendEntry rgb="224,198,8"  id="161"  />
            <LegendEntry rgb="224,191,8"  id="162"  />
            <LegendEntry rgb="224,185,8"  id="163"  />
            <LegendEntry rgb="224,180,8"  id="164"  />
            <LegendEntry rgb="224,174,8"  id="165"  />
            <LegendEntry rgb="224,166,8"  id="166"  />
            <LegendEntry rgb="224,159,8"  id="167"  />
            <LegendEntry rgb="224,151,8"  id="168"  />
            <LegendEntry rgb="224,143,8"  id="169"  />
            <LegendEntry rgb="224,135,8"  id="170"  />
            <LegendEntry rgb="224,127,8"  id="171"  />
            <LegendEntry rgb="224,119,8"  id="172"  />
            <LegendEntry rgb="224,111,8"  id="173"  />
            <LegendEntry rgb="224,103,8"  id="174"  />
            <LegendEntry rgb="224,95,8"  id="175"  />
            <LegendEntry rgb="224,89,8"  id="176"  />
            <LegendEntry rgb="224,84,8"  id="177"  />
            <LegendEntry rgb="224,78,8"  id="178"  />
            <LegendEntry rgb="223,70,8"  id="179"  />
            <LegendEntry rgb="223,63,8"  id="180"  />
            <LegendEntry rgb="223,55,8"  id="181"  />
            <LegendEntry rgb="222,46,8"  id="182"  />
            <LegendEntry rgb="221,37,8"  id="183"  />
            <LegendEntry rgb="219,28,8"  id="184"  />
            <LegendEntry rgb="216,19,8"  id="185"  />
            <LegendEntry rgb="213,12,8"  id="186"  />
            <LegendEntry rgb="209,9,8"  id="187"  />
            <LegendEntry rgb="204,8,8"  id="188"  />
            <LegendEntry rgb="200,8,8"  id="189"  />
            <LegendEntry rgb="196,8,8"  id="190"  />
            <LegendEntry rgb="190,8,8"  id="191"  />
            <LegendEntry rgb="182,8,8"  id="192"  />
            <LegendEntry rgb="175,8,8"  id="193"  />
            <LegendEntry rgb="167,8,8"  id="194"  />
            <LegendEntry rgb="159,8,8"  id="195"  />
            <LegendEntry rgb="151,8,8"  id="196"  />
            <LegendEntry rgb="143,8,8"  id="197"  />
            <LegendEntry rgb="135,8,8"  id="198"  />
            <LegendEntry rgb="127,8,8"  id="199"  />
            <LegendEntry rgb="120,8,8"  id="200"  />
            <LegendEntry rgb="115,8,8"  id="201"  />
            <LegendEntry rgb="110,8,8"  id="202"  />
            <LegendEntry rgb="104,8,8"  id="203"  />
            <LegendEntry rgb="108,13,13"  id="204"  />
            <LegendEntry rgb="112,19,19"  id="205"  />
            <LegendEntry rgb="114,22,22"  id="206"  />
            <LegendEntry rgb="115,26,26"  id="207"  />
            <LegendEntry rgb="118,30,30"  id="208"  />
            <LegendEntry rgb="119,34,33"  id="209"  />
            <LegendEntry rgb="121,38,38"  id="210"  />
            <LegendEntry rgb="123,41,41"  id="211"  />
            <LegendEntry rgb="125,45,45"  id="212"  />
            <LegendEntry rgb="127,49,49"  id="213"  />
            <LegendEntry rgb="128,52,53"  id="214"  />
            <LegendEntry rgb="130,56,56"  id="215"  />
            <LegendEntry rgb="132,60,60"  id="216"  />
            <LegendEntry rgb="134,64,63"  id="217"  />
            <LegendEntry rgb="136,67,67"  id="218"  />
            <LegendEntry rgb="138,71,70"  id="219"  />
            <LegendEntry rgb="140,75,74"  id="220"  />
            <LegendEntry rgb="142,79,78"  id="221"  />
            <LegendEntry rgb="143,82,82"  id="222"  />
            <LegendEntry rgb="145,85,85"  id="223"  />
            <LegendEntry rgb="147,89,90"  id="224"  />
            <LegendEntry rgb="149,93,93"  id="225"  />
            <LegendEntry rgb="150,97,97"  id="226"  />
            <LegendEntry rgb="152,100,100"  id="227"  />
            <LegendEntry rgb="154,104,104"  id="228"  />
            <LegendEntry rgb="156,107,108"  id="229"  />
            <LegendEntry rgb="158,112,111"  id="230"  />
            <LegendEntry rgb="160,115,115"  id="231"  />
            <LegendEntry rgb="162,119,119"  id="232"  />
            <LegendEntry rgb="164,123,123"  id="233"  />
            <LegendEntry rgb="165,126,126"  id="234"  />
            <LegendEntry rgb="168,130,130"  id="235"  />
            <LegendEntry rgb="169,134,134"  id="236"  />
            <LegendEntry rgb="170,138,137"  id="237"  />
            <LegendEntry rgb="173,141,141"  id="238"  />
            <LegendEntry rgb="175,145,145"  id="239"  />
            <LegendEntry rgb="176,149,149"  id="240"  />
            <LegendEntry rgb="178,153,153"  id="241"  />
            <LegendEntry rgb="181,156,156"  id="242"  />
            <LegendEntry rgb="182,159,159"  id="243"  />
            <LegendEntry rgb="183,163,163"  id="244"  />
            <LegendEntry rgb="185,167,167"  id="245"  />
            <LegendEntry rgb="188,170,171"  id="246"  />
            <LegendEntry rgb="190,174,174"  id="247"  />
            <LegendEntry rgb="191,178,178"  id="248"  />
            <LegendEntry rgb="193,182,182"  id="249"  />
            <LegendEntry rgb="195,185,185"  id="250"  />
            <LegendEntry rgb="197,189,189"  id="251"  />
            <LegendEntry rgb="199,192,193"  id="252"  />
            <LegendEntry rgb="200,197,197"  id="253"  />
            <LegendEntry rgb="202,200,201"  id="254"  />
            <LegendEntry rgb="204,204,204"  id="255"  />
        </Legend>
    </ColorMap>
    
</ColorMaps>
