{
    "layers": {
        "CERES_EBAF_Surface_CRE_Net_Longwave_Flux_Monthly": {
            "id":       "CERES_EBAF_Surface_CRE_Net_Longwave_Flux_Monthly",
            "title":    "Surface CRE Net Longwave Flux (Monthly, Energy Balanced and Filled)",
            "subtitle": "Terra / CERES",
            "tags":     "cloud radiative effect",
            "group":    "overlays",
            "layergroup": [
              "ceres"
            ],
            "product":  "",
            "startDate":"2000-03-01",
            "endDate":  "2011-11-30",
            "inactive": true,
            "wrapadjacentdays": true
        }
    }
}
